{
  "meta": {
    "ticker": "ADP",
    "name": "Automatic Data Processing, Inc.",
    "market": "NMS",
    "price": 210.6,
    "change": -0.72,
    "changePercent": -0.34
  },
  "score": {
    "total": 8,
    "stars": 0.5,
    "note": "/ 100 (Win Rate: 0%)"
  },
  "raw_metrics": {
    "targetMA_label": "Daily 50MA",
    "targetMA_price": 206.45,
    "maDistance_pct": 2.01,
    "bb2Confluence_pct": 9.07,
    "bb3Confluence_pct": 12.47,
    "maKnock_count": 0,
    "expectedRsi": 53.29
  },
  "metrics": {
    "maDistance": "+2.01%",
    "bbConfluence": "9.07%",
    "maKnock": "0 times recently",
    "expectedRsi": "53.29"
  },
  "resistances": {
    "horizontal": [
      {
        "price": 216.95,
        "touches": 4,
        "strength_score": 2.798
      },
      {
        "price": 258.09,
        "touches": 4,
        "strength_score": 1.403
      },
      {
        "price": 265.77,
        "touches": 2,
        "strength_score": 0.731
      },
      {
        "price": 224.64,
        "touches": 1,
        "strength_score": 0.623
      },
      {
        "price": 252.6,
        "touches": 1,
        "strength_score": 0.256
      }
    ],
    "trendline_clusters": [
      {
        "price": 214.8,
        "count": 2
      }
    ]
  },
  "summary": "The SwingRatings algorithm indicates that ADP is currently testing its Daily 50MA support zone near $206.45. Based on historical price action, bounces from this level have yielded a win rate of 0.0%. This is a fresh test of the support, suggesting that optimal buy-side liquidity remains intact. In the event of a successful bounce, traders should monitor overhead supply, particularly a primary horizontal resistance at $216.95 and a significant trendline confluence around $214.80 (formed by 2 points). This setup presents a structured risk-reward profile for swing positioning.",
  "chartData": {
    "candles": [
      {
        "time": "2025-09-30",
        "open": 284.2882099436688,
        "high": 289.62928231151574,
        "low": 280.8786123476294,
        "close": 289.2252502441406
      },
      {
        "time": "2025-10-01",
        "open": 288.22011639091494,
        "high": 289.3632249041414,
        "low": 285.35249616838166,
        "close": 287.3627624511719
      },
      {
        "time": "2025-10-02",
        "open": 285.0075749296122,
        "high": 286.5842772929027,
        "low": 282.24836834867597,
        "close": 285.6481018066406
      },
      {
        "time": "2025-10-03",
        "open": 285.7565230288416,
        "high": 288.12156160104223,
        "low": 283.6673750490824,
        "close": 287.067138671875
      },
      {
        "time": "2025-10-06",
        "open": 287.25438232650356,
        "high": 287.69784022897403,
        "low": 284.28821252883165,
        "close": 286.3182067871094
      },
      {
        "time": "2025-10-07",
        "open": 287.43174285626606,
        "high": 289.2351061818241,
        "low": 286.21967676092385,
        "close": 288.67340087890625
      },
      {
        "time": "2025-10-08",
        "open": 288.2989597445882,
        "high": 288.53545460204157,
        "low": 285.5988765449962,
        "close": 286.466064453125
      },
      {
        "time": "2025-10-09",
        "open": 286.2098232008825,
        "high": 287.09670893228804,
        "low": 281.2432210026745,
        "close": 281.7261047363281
      },
      {
        "time": "2025-10-10",
        "open": 282.6721115477189,
        "high": 283.60825700484145,
        "low": 280.5041419372603,
        "close": 281.0362854003906
      },
      {
        "time": "2025-10-13",
        "open": 281.05598651319616,
        "high": 282.65238684785766,
        "low": 278.769799529523,
        "close": 280.2085266113281
      },
      {
        "time": "2025-10-14",
        "open": 279.5285828518459,
        "high": 282.6228340784726,
        "low": 279.4891570190898,
        "close": 281.75567626953125
      },
      {
        "time": "2025-10-15",
        "open": 282.52434175868433,
        "high": 283.499913183189,
        "low": 278.8880827197645,
        "close": 280.0705871582031
      },
      {
        "time": "2025-10-16",
        "open": 280.1198501010763,
        "high": 280.3366470716253,
        "low": 275.35034682209755,
        "close": 276.0795593261719
      },
      {
        "time": "2025-10-17",
        "open": 276.8876157827773,
        "high": 278.77963467931977,
        "low": 275.92187838212453,
        "close": 277.1733703613281
      },
      {
        "time": "2025-10-20",
        "open": 277.5084140352483,
        "high": 279.607395987819,
        "low": 277.0846840835072,
        "close": 278.9077453613281
      },
      {
        "time": "2025-10-21",
        "open": 279.33148749209187,
        "high": 281.25309839605643,
        "low": 278.17854500819266,
        "close": 279.84393310546875
      },
      {
        "time": "2025-10-22",
        "open": 279.47928711059933,
        "high": 283.21409526611905,
        "low": 278.80919833346337,
        "close": 279.8143615722656
      },
      {
        "time": "2025-10-23",
        "open": 278.58255436960275,
        "high": 280.09026908383754,
        "low": 276.5722580595907,
        "close": 277.44927978515625
      },
      {
        "time": "2025-10-24",
        "open": 278.1391234500875,
        "high": 278.74022456966577,
        "low": 276.5919827557795,
        "close": 276.84820556640625
      },
      {
        "time": "2025-10-27",
        "open": 276.8777467531372,
        "high": 278.76979568824504,
        "low": 276.0105589109252,
        "close": 276.44415283203125
      },
      {
        "time": "2025-10-28",
        "open": 275.92188774839804,
        "high": 278.80920599907853,
        "low": 275.24193497631296,
        "close": 275.5572814941406
      },
      {
        "time": "2025-10-29",
        "open": 267.210634371196,
        "high": 268.8365965700223,
        "low": 256.44966787186337,
        "close": 257.4154052734375
      },
      {
        "time": "2025-10-30",
        "open": 258.4008695740616,
        "high": 262.04699255202166,
        "low": 256.42999879097,
        "close": 257.7209167480469
      },
      {
        "time": "2025-10-31",
        "open": 256.8340300991981,
        "high": 258.2628933685662,
        "low": 254.4295653455715,
        "close": 256.5088195800781
      },
      {
        "time": "2025-11-03",
        "open": 256.5088106143578,
        "high": 256.8832808605701,
        "low": 251.4436885328614,
        "close": 253.42442321777344
      },
      {
        "time": "2025-11-04",
        "open": 255.828853704417,
        "high": 258.4304174322452,
        "low": 253.12877050125283,
        "close": 255.44454956054688
      },
      {
        "time": "2025-11-05",
        "open": 252.73458857370008,
        "high": 256.9719482670573,
        "low": 252.310858618984,
        "close": 255.78944396972656
      },
      {
        "time": "2025-11-06",
        "open": 253.84813453043395,
        "high": 254.89269352298192,
        "low": 246.04347386874724,
        "close": 248.6844482421875
      },
      {
        "time": "2025-11-07",
        "open": 250.06405355675398,
        "high": 251.66046894999985,
        "low": 247.95522263947535,
        "close": 250.45823669433594
      },
      {
        "time": "2025-11-10",
        "open": 249.61077000320836,
        "high": 252.0447964508219,
        "low": 247.5216368962728,
        "close": 250.3596954345703
      },
      {
        "time": "2025-11-11",
        "open": 250.9016900256681,
        "high": 252.36999408083565,
        "low": 249.5812102919616,
        "close": 251.48309326171875
      },
      {
        "time": "2025-11-12",
        "open": 251.492950724316,
        "high": 252.59661841731605,
        "low": 249.7980007973367,
        "close": 250.84255981445312
      },
      {
        "time": "2025-11-13",
        "open": 249.16732687067744,
        "high": 251.3254175924565,
        "low": 246.99935713574922,
        "close": 250.9016876220703
      },
      {
        "time": "2025-11-14",
        "open": 250.90168976312148,
        "high": 251.9955235799695,
        "low": 247.56106459867473,
        "close": 249.40382385253906
      },
      {
        "time": "2025-11-17",
        "open": 249.1278973236537,
        "high": 249.86697380321198,
        "low": 246.70373489117028,
        "close": 247.24571228027344
      },
      {
        "time": "2025-11-18",
        "open": 247.36397549200638,
        "high": 247.79756943384336,
        "low": 243.60946937031244,
        "close": 246.0533447265625
      },
      {
        "time": "2025-11-19",
        "open": 246.61503883860937,
        "high": 247.6891747698413,
        "low": 243.57989623547232,
        "close": 246.7628631591797
      },
      {
        "time": "2025-11-20",
        "open": 248.1424574174526,
        "high": 248.26070484029398,
        "low": 244.16130547078401,
        "close": 245.43251037597656
      },
      {
        "time": "2025-11-21",
        "open": 246.14202980993846,
        "high": 250.75387486627383,
        "low": 245.43251518588687,
        "close": 249.43338012695312
      },
      {
        "time": "2025-11-24",
        "open": 248.94065299645408,
        "high": 249.10817518790142,
        "low": 244.71314230592108,
        "close": 246.45736694335938
      },
      {
        "time": "2025-11-25",
        "open": 247.3442754566564,
        "high": 256.21319370012213,
        "low": 247.0092310428975,
        "close": 252.57693481445312
      },
      {
        "time": "2025-11-26",
        "open": 253.23717551978302,
        "high": 253.65104150697144,
        "low": 250.359691196854,
        "close": 250.62576293945312
      },
      {
        "time": "2025-11-28",
        "open": 251.57178580330614,
        "high": 252.62619381683848,
        "low": 250.0049471936332,
        "close": 251.58164978027344
      },
      {
        "time": "2025-12-01",
        "open": 250.30055699590795,
        "high": 254.14374850996575,
        "low": 249.51220577758747,
        "close": 252.11375427246094
      },
      {
        "time": "2025-12-02",
        "open": 252.91195513082323,
        "high": 254.3506821994357,
        "low": 250.75386452790448,
        "close": 253.43423461914062
      },
      {
        "time": "2025-12-03",
        "open": 252.76414182241612,
        "high": 256.74530865599274,
        "low": 252.76414182241612,
        "close": 256.4299621582031
      },
      {
        "time": "2025-12-04",
        "open": 257.6519120917098,
        "high": 258.479674157344,
        "low": 254.58722266084155,
        "close": 255.62191772460938
      },
      {
        "time": "2025-12-05",
        "open": 255.62192632904305,
        "high": 258.93300477613286,
        "low": 255.56280261330042,
        "close": 257.8194580078125
      },
      {
        "time": "2025-12-08",
        "open": 257.06063419881207,
        "high": 257.3168569964917,
        "low": 253.8284076645621,
        "close": 254.92225646972656
      },
      {
        "time": "2025-12-09",
        "open": 255.31642353023287,
        "high": 257.1887445508678,
        "low": 254.232438705729,
        "close": 254.46896362304688
      },
      {
        "time": "2025-12-10",
        "open": 253.6116323174089,
        "high": 256.26245586781795,
        "low": 253.08935277437854,
        "close": 255.56280517578125
      },
      {
        "time": "2025-12-11",
        "open": 255.8091733193901,
        "high": 261.1305184947696,
        "low": 255.5726784454494,
        "close": 260.83489990234375
      },
      {
        "time": "2025-12-12",
        "open": 261.88615371664196,
        "high": 264.1673238612103,
        "low": 261.5786965227968,
        "close": 263.91937255859375
      },
      {
        "time": "2025-12-15",
        "open": 264.147474390613,
        "high": 265.6550377159885,
        "low": 262.40191776240613,
        "close": 262.77880859375
      },
      {
        "time": "2025-12-16",
        "open": 259.6347878534453,
        "high": 261.6382236448602,
        "low": 257.4429066353508,
        "close": 260.0216064453125
      },
      {
        "time": "2025-12-17",
        "open": 259.13888901258184,
        "high": 264.236782811294,
        "low": 258.8611847377393,
        "close": 263.2945556640625
      },
      {
        "time": "2025-12-18",
        "open": 260.973723900294,
        "high": 263.07634621670087,
        "low": 258.62315026794295,
        "close": 258.8314208984375
      },
      {
        "time": "2025-12-19",
        "open": 258.186749502708,
        "high": 258.86116980735613,
        "low": 254.9336294989705,
        "close": 255.8262481689453
      },
      {
        "time": "2025-12-22",
        "open": 255.82624340617713,
        "high": 259.3471398651096,
        "low": 255.50885846843005,
        "close": 257.6114807128906
      },
      {
        "time": "2025-12-23",
        "open": 258.13714952099974,
        "high": 258.2363361025724,
        "low": 254.4873133520881,
        "close": 254.9038848876953
      },
      {
        "time": "2025-12-24",
        "open": 254.41787033960136,
        "high": 256.87755824145444,
        "low": 253.2078818647545,
        "close": 255.9849395751953
      },
      {
        "time": "2025-12-26",
        "open": 255.7568197491532,
        "high": 256.9271427018021,
        "low": 255.29067006225137,
        "close": 256.7188720703125
      },
      {
        "time": "2025-12-29",
        "open": 257.02632200960295,
        "high": 258.69254754936355,
        "low": 256.2923958172666,
        "close": 257.4825439453125
      },
      {
        "time": "2025-12-30",
        "open": 256.50068230304805,
        "high": 258.52397359357417,
        "low": 256.44117640634107,
        "close": 257.4032287597656
      },
      {
        "time": "2025-12-31",
        "open": 256.8577294657028,
        "high": 257.37345728921395,
        "low": 254.98320305184686,
        "close": 255.1220703125
      },
      {
        "time": "2026-01-02",
        "open": 254.92370985670098,
        "high": 255.55847976417164,
        "low": 249.58779260856923,
        "close": 250.80772399902344
      },
      {
        "time": "2026-01-05",
        "open": 250.61927107759908,
        "high": 257.01642704795694,
        "low": 249.89525748245092,
        "close": 255.21133422851562
      },
      {
        "time": "2026-01-06",
        "open": 253.67404483756297,
        "high": 259.952174178337,
        "low": 253.37650022196394,
        "close": 258.9801940917969
      },
      {
        "time": "2026-01-07",
        "open": 259.8033971155621,
        "high": 260.32905268689916,
        "low": 257.1750889913828,
        "close": 259.1190490722656
      },
      {
        "time": "2026-01-08",
        "open": 258.1173220301018,
        "high": 264.8417605633562,
        "low": 257.47265465682045,
        "close": 263.492919921875
      },
      {
        "time": "2026-01-09",
        "open": 263.37387716817574,
        "high": 265.8831432889246,
        "low": 262.49118621755395,
        "close": 263.84002685546875
      },
      {
        "time": "2026-01-12",
        "open": 262.6300339596827,
        "high": 263.84996538718224,
        "low": 259.8232382503088,
        "close": 260.64642333984375
      },
      {
        "time": "2026-01-13",
        "open": 260.14060344122527,
        "high": 261.0629750451448,
        "low": 254.6162410206638,
        "close": 254.96337890625
      },
      {
        "time": "2026-01-14",
        "open": 254.53690962631768,
        "high": 256.9172361329616,
        "low": 254.09058516429346,
        "close": 256.38165283203125
      },
      {
        "time": "2026-01-15",
        "open": 259.0000484190933,
        "high": 261.4200254848964,
        "low": 257.00651009705336,
        "close": 258.0677490234375
      },
      {
        "time": "2026-01-16",
        "open": 257.8891841024005,
        "high": 258.9504229589711,
        "low": 255.45927945793233,
        "close": 258.3057556152344
      },
      {
        "time": "2026-01-20",
        "open": 256.34197254534587,
        "high": 257.7701745050459,
        "low": 252.1069750884886,
        "close": 253.009521484375
      },
      {
        "time": "2026-01-21",
        "open": 253.33680419739153,
        "high": 257.16518814790334,
        "low": 252.41443259200042,
        "close": 254.88401794433594
      },
      {
        "time": "2026-01-22",
        "open": 255.0923239223017,
        "high": 257.9288724257542,
        "low": 254.42780108315685,
        "close": 257.7304992675781
      },
      {
        "time": "2026-01-23",
        "open": 256.01469973506045,
        "high": 258.51403812450394,
        "low": 254.7749431449108,
        "close": 255.75682067871094
      },
      {
        "time": "2026-01-26",
        "open": 256.3122311149901,
        "high": 258.1073962494715,
        "low": 254.12034992221078,
        "close": 256.05438232421875
      },
      {
        "time": "2026-01-27",
        "open": 254.67574906267365,
        "high": 255.3501693636511,
        "low": 251.36312318346728,
        "close": 252.42434692382812
      },
      {
        "time": "2026-01-28",
        "open": 247.6041799364628,
        "high": 253.63435780225802,
        "low": 246.26525190040263,
        "close": 248.6356658935547
      },
      {
        "time": "2026-01-29",
        "open": 247.34631794148882,
        "high": 250.36139933100748,
        "low": 242.43688483685034,
        "close": 243.954345703125
      },
      {
        "time": "2026-01-30",
        "open": 243.0617193562909,
        "high": 244.97589622045456,
        "low": 241.68309553337374,
        "close": 244.79737854003906
      },
      {
        "time": "2026-02-02",
        "open": 244.579186447693,
        "high": 247.95131832339214,
        "low": 242.6352414531887,
        "close": 245.53131103515625
      },
      {
        "time": "2026-02-03",
        "open": 242.1492454492887,
        "high": 242.28809757877556,
        "low": 232.88578805727974,
        "close": 233.15357971191406
      },
      {
        "time": "2026-02-04",
        "open": 233.5701331455662,
        "high": 235.94054705494202,
        "low": 228.88881121959227,
        "close": 232.74693298339844
      },
      {
        "time": "2026-02-05",
        "open": 234.6412816631735,
        "high": 236.9224367046679,
        "low": 230.50545569596792,
        "close": 232.072509765625
      },
      {
        "time": "2026-02-06",
        "open": 232.26094851532156,
        "high": 233.7585841434729,
        "low": 228.3929140549417,
        "close": 229.4640655517578
      },
      {
        "time": "2026-02-09",
        "open": 229.4640714365129,
        "high": 229.4640714365129,
        "low": 223.0867555818138,
        "close": 224.76290893554688
      },
      {
        "time": "2026-02-10",
        "open": 222.17429075720062,
        "high": 225.25880571993918,
        "low": 221.6089696287712,
        "close": 223.6818389892578
      },
      {
        "time": "2026-02-11",
        "open": 223.68184029511266,
        "high": 224.22733621783252,
        "low": 214.8746046955556,
        "close": 215.78707885742188
      },
      {
        "time": "2026-02-12",
        "open": 214.8051869553152,
        "high": 215.27133664239994,
        "low": 206.91041035598914,
        "close": 208.23944091796875
      },
      {
        "time": "2026-02-13",
        "open": 208.94360894030675,
        "high": 211.611567468103,
        "low": 207.33688928780367,
        "close": 210.37181091308594
      },
      {
        "time": "2026-02-17",
        "open": 210.68917981859357,
        "high": 213.08936181651663,
        "low": 208.49729871361626,
        "close": 211.3338623046875
      },
      {
        "time": "2026-02-18",
        "open": 211.09582399648716,
        "high": 216.0449376003711,
        "low": 209.88582039099845,
        "close": 215.43002319335938
      },
      {
        "time": "2026-02-19",
        "open": 215.43002400612127,
        "high": 217.05658400318163,
        "low": 212.14713593159212,
        "close": 214.20018005371094
      },
      {
        "time": "2026-02-20",
        "open": 213.59518472750105,
        "high": 214.40845718382607,
        "low": 211.01648495781708,
        "close": 212.7124786376953
      },
      {
        "time": "2026-02-23",
        "open": 211.50247791228492,
        "high": 212.44468991023254,
        "low": 203.64738183822774,
        "close": 204.04409790039062
      },
      {
        "time": "2026-02-24",
        "open": 204.0440848651875,
        "high": 206.0772886048149,
        "low": 201.59432474677612,
        "close": 203.99449157714844
      },
      {
        "time": "2026-02-25",
        "open": 204.4209837050926,
        "high": 212.58353679582189,
        "low": 203.5680305721323,
        "close": 212.49427795410156
      },
      {
        "time": "2026-02-26",
        "open": 213.01993768426507,
        "high": 219.91298138123287,
        "low": 213.01993768426507,
        "close": 216.5706024169922
      },
      {
        "time": "2026-02-27",
        "open": 213.14887422118215,
        "high": 214.0315803061877,
        "low": 207.2079552053601,
        "close": 212.60337829589844
      },
      {
        "time": "2026-03-02",
        "open": 210.84787270534278,
        "high": 214.47788352214047,
        "low": 208.99320174612376,
        "close": 213.2083740234375
      },
      {
        "time": "2026-03-03",
        "open": 212.8612386916887,
        "high": 215.7672359543788,
        "low": 211.75042165042,
        "close": 214.4977264404297
      },
      {
        "time": "2026-03-04",
        "open": 215.06304718410817,
        "high": 216.5705954044048,
        "low": 212.86123831424968,
        "close": 215.38043212890625
      },
      {
        "time": "2026-03-05",
        "open": 215.70773353775755,
        "high": 221.61888446979296,
        "low": 215.46969482489973,
        "close": 220.87503051757812
      },
      {
        "time": "2026-03-06",
        "open": 219.04020224804182,
        "high": 224.6438960292685,
        "low": 217.4929732981413,
        "close": 224.3860321044922
      },
      {
        "time": "2026-03-09",
        "open": 222.72971044024197,
        "high": 223.64216944675084,
        "low": 218.57404405523368,
        "close": 221.2122344970703
      },
      {
        "time": "2026-03-10",
        "open": 220.14109687643221,
        "high": 220.58740620595384,
        "low": 210.75861268353088,
        "close": 215.5886993408203
      },
      {
        "time": "2026-03-11",
        "open": 216.0945310265945,
        "high": 217.99879527568572,
        "low": 209.6874625027407,
        "close": 211.2545166015625
      },
      {
        "time": "2026-03-12",
        "open": 210.95697766155908,
        "high": 214.2299380755743,
        "low": 205.58139492034206,
        "close": 205.75
      },
      {
        "time": "2026-03-13",
        "open": 205.75999450683594,
        "high": 209.14999389648438,
        "low": 205.52999877929688,
        "close": 208.52000427246094
      },
      {
        "time": "2026-03-16",
        "open": 208.4499969482422,
        "high": 210.9499969482422,
        "low": 207.58999633789062,
        "close": 209.11000061035156
      },
      {
        "time": "2026-03-17",
        "open": 210.19000244140625,
        "high": 213.4199981689453,
        "low": 208.8800048828125,
        "close": 209.72999572753906
      },
      {
        "time": "2026-03-18",
        "open": 207.36000061035156,
        "high": 211.05999755859375,
        "low": 207.36000061035156,
        "close": 208.27999877929688
      },
      {
        "time": "2026-03-19",
        "open": 210.74000549316406,
        "high": 214.3000030517578,
        "low": 209.0,
        "close": 210.66000366210938
      },
      {
        "time": "2026-03-20",
        "open": 211.27000427246094,
        "high": 212.7899932861328,
        "low": 208.55999755859375,
        "close": 208.69000244140625
      },
      {
        "time": "2026-03-23",
        "open": 209.5800018310547,
        "high": 211.72999572753906,
        "low": 208.00999450683594,
        "close": 209.7100067138672
      },
      {
        "time": "2026-03-24",
        "open": 209.3300018310547,
        "high": 210.2899932861328,
        "low": 204.02999877929688,
        "close": 204.88999938964844
      },
      {
        "time": "2026-03-25",
        "open": 206.25999450683594,
        "high": 209.49000549316406,
        "low": 198.58999633789062,
        "close": 202.11000061035156
      },
      {
        "time": "2026-03-26",
        "open": 202.02999877929688,
        "high": 208.19000244140625,
        "low": 201.9199981689453,
        "close": 204.50999450683594
      },
      {
        "time": "2026-03-27",
        "open": 203.47999572753906,
        "high": 204.58999633789062,
        "low": 199.19000244140625,
        "close": 201.25
      },
      {
        "time": "2026-03-30",
        "open": 203.19000244140625,
        "high": 206.66000366210938,
        "low": 202.5,
        "close": 205.47000122070312
      },
      {
        "time": "2026-03-31",
        "open": 206.91000366210938,
        "high": 208.1699981689453,
        "low": 202.35000610351562,
        "close": 203.17999267578125
      },
      {
        "time": "2026-04-01",
        "open": 203.35000610351562,
        "high": 204.44000244140625,
        "low": 197.0800018310547,
        "close": 201.27999877929688
      },
      {
        "time": "2026-04-02",
        "open": 201.25,
        "high": 204.3000030517578,
        "low": 199.16000366210938,
        "close": 204.00999450683594
      },
      {
        "time": "2026-04-06",
        "open": 203.49000549316406,
        "high": 205.35000610351562,
        "low": 202.02000427246094,
        "close": 204.33999633789062
      },
      {
        "time": "2026-04-07",
        "open": 203.88999938964844,
        "high": 205.44000244140625,
        "low": 202.8300018310547,
        "close": 203.61000061035156
      },
      {
        "time": "2026-04-08",
        "open": 204.50999450683594,
        "high": 206.5399932861328,
        "low": 199.3800048828125,
        "close": 200.77999877929688
      },
      {
        "time": "2026-04-09",
        "open": 199.77999877929688,
        "high": 199.82000732421875,
        "low": 194.5399932861328,
        "close": 196.02000427246094
      },
      {
        "time": "2026-04-10",
        "open": 195.99000549316406,
        "high": 196.0500030517578,
        "low": 188.16000366210938,
        "close": 188.7899932861328
      },
      {
        "time": "2026-04-13",
        "open": 188.25999450683594,
        "high": 195.47000122070312,
        "low": 188.25999450683594,
        "close": 195.3800048828125
      },
      {
        "time": "2026-04-14",
        "open": 195.69000244140625,
        "high": 197.69000244140625,
        "low": 194.13999938964844,
        "close": 195.0800018310547
      },
      {
        "time": "2026-04-15",
        "open": 196.05999755859375,
        "high": 198.8800048828125,
        "low": 194.52999877929688,
        "close": 196.9199981689453
      },
      {
        "time": "2026-04-16",
        "open": 197.85000610351562,
        "high": 201.39999389648438,
        "low": 197.85000610351562,
        "close": 200.38999938964844
      },
      {
        "time": "2026-04-17",
        "open": 201.64999389648438,
        "high": 202.13999938964844,
        "low": 198.3300018310547,
        "close": 200.47000122070312
      },
      {
        "time": "2026-04-20",
        "open": 200.47000122070312,
        "high": 203.38999938964844,
        "low": 200.4600067138672,
        "close": 202.38999938964844
      },
      {
        "time": "2026-04-21",
        "open": 202.24000549316406,
        "high": 206.10000610351562,
        "low": 201.82000732421875,
        "close": 202.8699951171875
      },
      {
        "time": "2026-04-22",
        "open": 203.17999267578125,
        "high": 203.9499969482422,
        "low": 200.6199951171875,
        "close": 201.69000244140625
      },
      {
        "time": "2026-04-23",
        "open": 200.11000061035156,
        "high": 200.89999389648438,
        "low": 195.11000061035156,
        "close": 198.52999877929688
      },
      {
        "time": "2026-04-24",
        "open": 196.9600067138672,
        "high": 197.6300048828125,
        "low": 194.89999389648438,
        "close": 196.52999877929688
      },
      {
        "time": "2026-04-27",
        "open": 195.85000610351562,
        "high": 199.4499969482422,
        "low": 195.6999969482422,
        "close": 197.22999572753906
      },
      {
        "time": "2026-04-28",
        "open": 199.69000244140625,
        "high": 201.52000427246094,
        "low": 197.60000610351562,
        "close": 199.1699981689453
      },
      {
        "time": "2026-04-29",
        "open": 207.77999877929688,
        "high": 215.1699981689453,
        "low": 205.05999755859375,
        "close": 215.05999755859375
      },
      {
        "time": "2026-04-30",
        "open": 212.64999389648438,
        "high": 215.05999755859375,
        "low": 210.3000030517578,
        "close": 211.94000244140625
      },
      {
        "time": "2026-05-01",
        "open": 215.02000427246094,
        "high": 216.5500030517578,
        "low": 209.1199951171875,
        "close": 214.2100067138672
      },
      {
        "time": "2026-05-04",
        "open": 213.1199951171875,
        "high": 216.10000610351562,
        "low": 210.6300048828125,
        "close": 211.32000732421875
      },
      {
        "time": "2026-05-05",
        "open": 210.11000061035156,
        "high": 211.22999572753906,
        "low": 206.74000549316406,
        "close": 210.60000610351562
      }
    ],
    "ma_target": [
      {
        "time": "2025-09-30",
        "value": 294.4751989746094
      },
      {
        "time": "2025-10-01",
        "value": 294.28196533203123
      },
      {
        "time": "2025-10-02",
        "value": 294.02993041992187
      },
      {
        "time": "2025-10-03",
        "value": 293.7668664550781
      },
      {
        "time": "2025-10-06",
        "value": 293.44196350097656
      },
      {
        "time": "2025-10-07",
        "value": 293.1982800292969
      },
      {
        "time": "2025-10-08",
        "value": 292.8761376953125
      },
      {
        "time": "2025-10-09",
        "value": 292.41410095214843
      },
      {
        "time": "2025-10-10",
        "value": 291.96650146484376
      },
      {
        "time": "2025-10-13",
        "value": 291.6799853515625
      },
      {
        "time": "2025-10-14",
        "value": 291.38872680664065
      },
      {
        "time": "2025-10-15",
        "value": 291.11905883789063
      },
      {
        "time": "2025-10-16",
        "value": 290.72643493652345
      },
      {
        "time": "2025-10-17",
        "value": 290.31941467285156
      },
      {
        "time": "2025-10-20",
        "value": 289.9015936279297
      },
      {
        "time": "2025-10-21",
        "value": 289.5434747314453
      },
      {
        "time": "2025-10-22",
        "value": 289.2649572753906
      },
      {
        "time": "2025-10-23",
        "value": 288.83482849121094
      },
      {
        "time": "2025-10-24",
        "value": 288.4567932128906
      },
      {
        "time": "2025-10-27",
        "value": 288.06851989746093
      },
      {
        "time": "2025-10-28",
        "value": 287.64564697265627
      },
      {
        "time": "2025-10-29",
        "value": 286.79974365234375
      },
      {
        "time": "2025-10-30",
        "value": 285.8950518798828
      },
      {
        "time": "2025-10-31",
        "value": 285.0463104248047
      },
      {
        "time": "2025-11-03",
        "value": 284.07686431884764
      },
      {
        "time": "2025-11-04",
        "value": 283.228405456543
      },
      {
        "time": "2025-11-05",
        "value": 282.39449096679687
      },
      {
        "time": "2025-11-06",
        "value": 281.4255352783203
      },
      {
        "time": "2025-11-07",
        "value": 280.4722512817383
      },
      {
        "time": "2025-11-10",
        "value": 279.5179779052734
      },
      {
        "time": "2025-11-11",
        "value": 278.6700897216797
      },
      {
        "time": "2025-11-12",
        "value": 277.82723327636717
      },
      {
        "time": "2025-11-13",
        "value": 276.93987518310547
      },
      {
        "time": "2025-11-14",
        "value": 276.1249072265625
      },
      {
        "time": "2025-11-17",
        "value": 275.21854400634766
      },
      {
        "time": "2025-11-18",
        "value": 274.3116665649414
      },
      {
        "time": "2025-11-19",
        "value": 273.514072265625
      },
      {
        "time": "2025-11-20",
        "value": 272.57928863525393
      },
      {
        "time": "2025-11-21",
        "value": 271.7834512329102
      },
      {
        "time": "2025-11-24",
        "value": 270.9799270629883
      },
      {
        "time": "2025-11-25",
        "value": 270.3417593383789
      },
      {
        "time": "2025-11-26",
        "value": 269.66338592529297
      },
      {
        "time": "2025-11-28",
        "value": 268.9607708740234
      },
      {
        "time": "2025-12-01",
        "value": 268.24810394287107
      },
      {
        "time": "2025-12-02",
        "value": 267.52912994384764
      },
      {
        "time": "2025-12-03",
        "value": 266.95777435302733
      },
      {
        "time": "2025-12-04",
        "value": 266.3251248168945
      },
      {
        "time": "2025-12-05",
        "value": 265.78786529541014
      },
      {
        "time": "2025-12-08",
        "value": 265.14043395996094
      },
      {
        "time": "2025-12-09",
        "value": 264.4618634033203
      },
      {
        "time": "2025-12-10",
        "value": 263.78861450195313
      },
      {
        "time": "2025-12-11",
        "value": 263.25805725097655
      },
      {
        "time": "2025-12-12",
        "value": 262.82348266601565
      },
      {
        "time": "2025-12-15",
        "value": 262.3377160644531
      },
      {
        "time": "2025-12-16",
        "value": 261.81178405761716
      },
      {
        "time": "2025-12-17",
        "value": 261.3042071533203
      },
      {
        "time": "2025-12-18",
        "value": 260.75151428222654
      },
      {
        "time": "2025-12-19",
        "value": 260.2335171508789
      },
      {
        "time": "2025-12-22",
        "value": 259.76502105712893
      },
      {
        "time": "2025-12-23",
        "value": 259.25892822265627
      },
      {
        "time": "2025-12-24",
        "value": 258.7435134887695
      },
      {
        "time": "2025-12-26",
        "value": 258.2764791870117
      },
      {
        "time": "2025-12-29",
        "value": 257.9045388793945
      },
      {
        "time": "2025-12-30",
        "value": 257.50913604736326
      },
      {
        "time": "2025-12-31",
        "value": 257.0334225463867
      },
      {
        "time": "2026-01-02",
        "value": 256.4526983642578
      },
      {
        "time": "2026-01-05",
        "value": 255.9606378173828
      },
      {
        "time": "2026-01-06",
        "value": 255.59125610351563
      },
      {
        "time": "2026-01-07",
        "value": 255.2366729736328
      },
      {
        "time": "2026-01-08",
        "value": 254.9776483154297
      },
      {
        "time": "2026-01-09",
        "value": 254.74330322265624
      },
      {
        "time": "2026-01-12",
        "value": 254.80792358398438
      },
      {
        "time": "2026-01-13",
        "value": 254.75277282714845
      },
      {
        "time": "2026-01-14",
        "value": 254.7502294921875
      },
      {
        "time": "2026-01-15",
        "value": 254.8430960083008
      },
      {
        "time": "2026-01-16",
        "value": 254.90032012939454
      },
      {
        "time": "2026-01-20",
        "value": 254.8447216796875
      },
      {
        "time": "2026-01-21",
        "value": 254.96871307373047
      },
      {
        "time": "2026-01-22",
        "value": 255.11415832519532
      },
      {
        "time": "2026-01-23",
        "value": 255.22210083007812
      },
      {
        "time": "2026-01-26",
        "value": 255.31352661132811
      },
      {
        "time": "2026-01-27",
        "value": 255.34516235351563
      },
      {
        "time": "2026-01-28",
        "value": 255.2998419189453
      },
      {
        "time": "2026-01-29",
        "value": 255.19085235595702
      },
      {
        "time": "2026-01-30",
        "value": 255.14188568115233
      },
      {
        "time": "2026-02-02",
        "value": 255.13144500732423
      },
      {
        "time": "2026-02-03",
        "value": 254.8592593383789
      },
      {
        "time": "2026-02-04",
        "value": 254.60554779052734
      },
      {
        "time": "2026-02-05",
        "value": 254.25833038330077
      },
      {
        "time": "2026-02-06",
        "value": 253.91846435546876
      },
      {
        "time": "2026-02-09",
        "value": 253.36218383789063
      },
      {
        "time": "2026-02-10",
        "value": 252.82330535888673
      },
      {
        "time": "2026-02-11",
        "value": 252.1074139404297
      },
      {
        "time": "2026-02-12",
        "value": 251.22992767333983
      },
      {
        "time": "2026-02-13",
        "value": 250.36867919921875
      },
      {
        "time": "2026-02-17",
        "value": 249.46675720214844
      },
      {
        "time": "2026-02-18",
        "value": 248.66291931152344
      },
      {
        "time": "2026-02-19",
        "value": 247.7905337524414
      },
      {
        "time": "2026-02-20",
        "value": 246.9463381958008
      },
      {
        "time": "2026-02-23",
        "value": 245.93784088134765
      },
      {
        "time": "2026-02-24",
        "value": 244.906474609375
      },
      {
        "time": "2026-02-25",
        "value": 243.93966217041014
      },
      {
        "time": "2026-02-26",
        "value": 242.99268676757814
      },
      {
        "time": "2026-02-27",
        "value": 241.98917816162108
      },
      {
        "time": "2026-03-02",
        "value": 241.0529135131836
      },
      {
        "time": "2026-03-03",
        "value": 240.07697692871093
      },
      {
        "time": "2026-03-04",
        "value": 239.2079571533203
      },
      {
        "time": "2026-03-05",
        "value": 238.50893280029297
      },
      {
        "time": "2026-03-06",
        "value": 237.844423828125
      },
      {
        "time": "2026-03-09",
        "value": 237.1705908203125
      },
      {
        "time": "2026-03-10",
        "value": 236.362666015625
      },
      {
        "time": "2026-03-11",
        "value": 235.45337890625
      },
      {
        "time": "2026-03-12",
        "value": 234.41872802734375
      },
      {
        "time": "2026-03-13",
        "value": 233.44106353759764
      },
      {
        "time": "2026-03-16",
        "value": 232.52082214355468
      },
      {
        "time": "2026-03-17",
        "value": 231.699267578125
      },
      {
        "time": "2026-03-18",
        "value": 230.76064086914062
      },
      {
        "time": "2026-03-19",
        "value": 229.79423706054686
      },
      {
        "time": "2026-03-20",
        "value": 228.78565612792968
      },
      {
        "time": "2026-03-23",
        "value": 227.70999786376953
      },
      {
        "time": "2026-03-24",
        "value": 226.53099731445312
      },
      {
        "time": "2026-03-25",
        "value": 225.36026885986328
      },
      {
        "time": "2026-03-26",
        "value": 224.351201171875
      },
      {
        "time": "2026-03-27",
        "value": 223.24856811523438
      },
      {
        "time": "2026-03-30",
        "value": 222.1966131591797
      },
      {
        "time": "2026-03-31",
        "value": 221.09409790039064
      },
      {
        "time": "2026-04-01",
        "value": 220.05950744628908
      },
      {
        "time": "2026-04-02",
        "value": 219.04202697753905
      },
      {
        "time": "2026-04-06",
        "value": 217.9742169189453
      },
      {
        "time": "2026-04-07",
        "value": 216.93128051757813
      },
      {
        "time": "2026-04-08",
        "value": 215.8257928466797
      },
      {
        "time": "2026-04-09",
        "value": 214.69770599365233
      },
      {
        "time": "2026-04-10",
        "value": 213.5007925415039
      },
      {
        "time": "2026-04-13",
        "value": 212.52930572509766
      },
      {
        "time": "2026-04-14",
        "value": 211.53495819091796
      },
      {
        "time": "2026-04-15",
        "value": 210.56273193359374
      },
      {
        "time": "2026-04-16",
        "value": 209.90746032714844
      },
      {
        "time": "2026-04-17",
        "value": 209.26192169189454
      },
      {
        "time": "2026-04-20",
        "value": 208.668271484375
      },
      {
        "time": "2026-04-21",
        "value": 208.1363900756836
      },
      {
        "time": "2026-04-22",
        "value": 207.67493194580078
      },
      {
        "time": "2026-04-23",
        "value": 207.17189514160157
      },
      {
        "time": "2026-04-24",
        "value": 206.78675354003906
      },
      {
        "time": "2026-04-27",
        "value": 206.56656463623048
      },
      {
        "time": "2026-04-28",
        "value": 206.34252838134765
      },
      {
        "time": "2026-04-29",
        "value": 206.41705108642577
      },
      {
        "time": "2026-04-30",
        "value": 206.34725067138672
      },
      {
        "time": "2026-05-01",
        "value": 206.34744720458986
      },
      {
        "time": "2026-05-04",
        "value": 206.31959777832031
      },
      {
        "time": "2026-05-05",
        "value": 206.4507159423828
      }
    ],
    "bbLower": [
      {
        "time": "2025-09-30",
        "value": 282.57061869330965
      },
      {
        "time": "2025-10-01",
        "value": 282.62124920296714
      },
      {
        "time": "2025-10-02",
        "value": 283.0174926248926
      },
      {
        "time": "2025-10-03",
        "value": 282.97498929566154
      },
      {
        "time": "2025-10-06",
        "value": 283.2062255350522
      },
      {
        "time": "2025-10-07",
        "value": 283.44705193969367
      },
      {
        "time": "2025-10-08",
        "value": 283.4320185669745
      },
      {
        "time": "2025-10-09",
        "value": 282.9072888073527
      },
      {
        "time": "2025-10-10",
        "value": 281.9503668171345
      },
      {
        "time": "2025-10-13",
        "value": 280.89086130258704
      },
      {
        "time": "2025-10-14",
        "value": 280.4641563638017
      },
      {
        "time": "2025-10-15",
        "value": 279.6993432126969
      },
      {
        "time": "2025-10-16",
        "value": 277.8871543823851
      },
      {
        "time": "2025-10-17",
        "value": 276.69833709896733
      },
      {
        "time": "2025-10-20",
        "value": 276.13892339295035
      },
      {
        "time": "2025-10-21",
        "value": 275.6915098336857
      },
      {
        "time": "2025-10-22",
        "value": 275.3122883115063
      },
      {
        "time": "2025-10-23",
        "value": 274.57580868012656
      },
      {
        "time": "2025-10-24",
        "value": 273.8837224479619
      },
      {
        "time": "2025-10-27",
        "value": 273.34618614421123
      },
      {
        "time": "2025-10-28",
        "value": 272.9311087040566
      },
      {
        "time": "2025-10-29",
        "value": 266.8568059074985
      },
      {
        "time": "2025-10-30",
        "value": 262.59296878194215
      },
      {
        "time": "2025-10-31",
        "value": 258.96191117274077
      },
      {
        "time": "2025-11-03",
        "value": 255.1916029343181
      },
      {
        "time": "2025-11-04",
        "value": 252.7894315980371
      },
      {
        "time": "2025-11-05",
        "value": 250.7867750015431
      },
      {
        "time": "2025-11-06",
        "value": 247.3585849581785
      },
      {
        "time": "2025-11-07",
        "value": 244.83922335067794
      },
      {
        "time": "2025-11-10",
        "value": 242.6706949319832
      },
      {
        "time": "2025-11-11",
        "value": 241.17888997699617
      },
      {
        "time": "2025-11-12",
        "value": 239.8159400726537
      },
      {
        "time": "2025-11-13",
        "value": 238.51752731617145
      },
      {
        "time": "2025-11-14",
        "value": 237.34030293739426
      },
      {
        "time": "2025-11-17",
        "value": 236.33767403627726
      },
      {
        "time": "2025-11-18",
        "value": 235.72908967640507
      },
      {
        "time": "2025-11-19",
        "value": 235.81204544721987
      },
      {
        "time": "2025-11-20",
        "value": 235.968249227168
      },
      {
        "time": "2025-11-21",
        "value": 237.2680825470463
      },
      {
        "time": "2025-11-24",
        "value": 239.18780942757297
      },
      {
        "time": "2025-11-25",
        "value": 243.54460840753313
      },
      {
        "time": "2025-11-26",
        "value": 243.77710139351913
      },
      {
        "time": "2025-11-28",
        "value": 244.2153345821946
      },
      {
        "time": "2025-12-01",
        "value": 244.5770766293174
      },
      {
        "time": "2025-12-02",
        "value": 244.57646968064796
      },
      {
        "time": "2025-12-03",
        "value": 244.43261617202504
      },
      {
        "time": "2025-12-04",
        "value": 244.45517536270708
      },
      {
        "time": "2025-12-05",
        "value": 244.11299952816324
      },
      {
        "time": "2025-12-08",
        "value": 244.09492238882518
      },
      {
        "time": "2025-12-09",
        "value": 244.14254818808936
      },
      {
        "time": "2025-12-10",
        "value": 244.09142039893558
      },
      {
        "time": "2025-12-11",
        "value": 243.51790388519674
      },
      {
        "time": "2025-12-12",
        "value": 242.6823379276414
      },
      {
        "time": "2025-12-15",
        "value": 242.51207136412154
      },
      {
        "time": "2025-12-16",
        "value": 243.12449915104085
      },
      {
        "time": "2025-12-17",
        "value": 243.85853042252364
      },
      {
        "time": "2025-12-18",
        "value": 244.96528093007936
      },
      {
        "time": "2025-12-19",
        "value": 246.53037386050138
      },
      {
        "time": "2025-12-22",
        "value": 247.3918207648898
      },
      {
        "time": "2025-12-23",
        "value": 248.994387108319
      },
      {
        "time": "2025-12-24",
        "value": 249.38706410564097
      },
      {
        "time": "2025-12-26",
        "value": 250.2549184705089
      },
      {
        "time": "2025-12-29",
        "value": 251.03904785895065
      },
      {
        "time": "2025-12-30",
        "value": 251.78573692722665
      },
      {
        "time": "2025-12-31",
        "value": 252.07111173803625
      },
      {
        "time": "2026-01-02",
        "value": 251.04661992115174
      },
      {
        "time": "2026-01-05",
        "value": 250.99979205865588
      },
      {
        "time": "2026-01-06",
        "value": 251.0258456183581
      },
      {
        "time": "2026-01-07",
        "value": 251.3159604521135
      },
      {
        "time": "2026-01-08",
        "value": 251.48927622821802
      },
      {
        "time": "2026-01-09",
        "value": 251.58977167975377
      },
      {
        "time": "2026-01-12",
        "value": 251.59182837732308
      },
      {
        "time": "2026-01-13",
        "value": 251.4218550771519
      },
      {
        "time": "2026-01-14",
        "value": 251.4109988728655
      },
      {
        "time": "2026-01-15",
        "value": 251.3905317160995
      },
      {
        "time": "2026-01-16",
        "value": 251.66445615635018
      },
      {
        "time": "2026-01-20",
        "value": 251.09609584541812
      },
      {
        "time": "2026-01-21",
        "value": 250.99314180758057
      },
      {
        "time": "2026-01-22",
        "value": 250.99707705340228
      },
      {
        "time": "2026-01-23",
        "value": 251.09103196352171
      },
      {
        "time": "2026-01-26",
        "value": 251.09718372587926
      },
      {
        "time": "2026-01-27",
        "value": 250.53749191839597
      },
      {
        "time": "2026-01-28",
        "value": 249.14812375569696
      },
      {
        "time": "2026-01-29",
        "value": 246.68250756505438
      },
      {
        "time": "2026-01-30",
        "value": 244.97341488855747
      },
      {
        "time": "2026-02-02",
        "value": 244.0158462946048
      },
      {
        "time": "2026-02-03",
        "value": 239.35807729228694
      },
      {
        "time": "2026-02-04",
        "value": 235.5767351806258
      },
      {
        "time": "2026-02-05",
        "value": 232.30632761625722
      },
      {
        "time": "2026-02-06",
        "value": 229.2257351225606
      },
      {
        "time": "2026-02-09",
        "value": 225.67065261706685
      },
      {
        "time": "2026-02-10",
        "value": 222.3338412798629
      },
      {
        "time": "2026-02-11",
        "value": 217.40525107791302
      },
      {
        "time": "2026-02-12",
        "value": 211.46814422820967
      },
      {
        "time": "2026-02-13",
        "value": 207.2194864521423
      },
      {
        "time": "2026-02-17",
        "value": 203.9766803651658
      },
      {
        "time": "2026-02-18",
        "value": 201.74147501751108
      },
      {
        "time": "2026-02-19",
        "value": 199.88439910564264
      },
      {
        "time": "2026-02-20",
        "value": 198.61643366317747
      },
      {
        "time": "2026-02-23",
        "value": 196.23797939519255
      },
      {
        "time": "2026-02-24",
        "value": 194.75597357315758
      },
      {
        "time": "2026-02-25",
        "value": 194.9484884527066
      },
      {
        "time": "2026-02-26",
        "value": 195.70751644616618
      },
      {
        "time": "2026-02-27",
        "value": 195.95880016190705
      },
      {
        "time": "2026-03-02",
        "value": 197.02377846369257
      },
      {
        "time": "2026-03-03",
        "value": 199.31095313728093
      },
      {
        "time": "2026-03-04",
        "value": 200.02449044387117
      },
      {
        "time": "2026-03-05",
        "value": 201.12591880325274
      },
      {
        "time": "2026-03-06",
        "value": 202.17740602598926
      },
      {
        "time": "2026-03-09",
        "value": 203.1488828967375
      },
      {
        "time": "2026-03-10",
        "value": 203.61186922256533
      },
      {
        "time": "2026-03-11",
        "value": 203.82236582450707
      },
      {
        "time": "2026-03-12",
        "value": 202.78868823868095
      },
      {
        "time": "2026-03-13",
        "value": 202.82878746420346
      },
      {
        "time": "2026-03-16",
        "value": 202.68228126136833
      },
      {
        "time": "2026-03-17",
        "value": 202.5231933649899
      },
      {
        "time": "2026-03-18",
        "value": 202.02513495504022
      },
      {
        "time": "2026-03-19",
        "value": 201.83476013296203
      },
      {
        "time": "2026-03-20",
        "value": 201.5035734641539
      },
      {
        "time": "2026-03-23",
        "value": 202.38984813418807
      },
      {
        "time": "2026-03-24",
        "value": 202.57922676334303
      },
      {
        "time": "2026-03-25",
        "value": 201.05830531213797
      },
      {
        "time": "2026-03-26",
        "value": 200.1740868653246
      },
      {
        "time": "2026-03-27",
        "value": 198.77112033340984
      },
      {
        "time": "2026-03-30",
        "value": 198.2020124789883
      },
      {
        "time": "2026-03-31",
        "value": 197.37010928788186
      },
      {
        "time": "2026-04-01",
        "value": 196.36886688606756
      },
      {
        "time": "2026-04-02",
        "value": 196.48310351380954
      },
      {
        "time": "2026-04-06",
        "value": 197.84809752663836
      },
      {
        "time": "2026-04-07",
        "value": 199.18879114043432
      },
      {
        "time": "2026-04-08",
        "value": 199.27726659003883
      },
      {
        "time": "2026-04-09",
        "value": 197.71303793646578
      },
      {
        "time": "2026-04-10",
        "value": 194.01461044734393
      },
      {
        "time": "2026-04-13",
        "value": 192.86394741265318
      },
      {
        "time": "2026-04-14",
        "value": 191.86716961486636
      },
      {
        "time": "2026-04-15",
        "value": 191.4040086918955
      },
      {
        "time": "2026-04-16",
        "value": 191.347165924438
      },
      {
        "time": "2026-04-17",
        "value": 191.6374760726537
      },
      {
        "time": "2026-04-20",
        "value": 191.90508747242
      },
      {
        "time": "2026-04-21",
        "value": 192.41754984166946
      },
      {
        "time": "2026-04-22",
        "value": 192.46787079550685
      },
      {
        "time": "2026-04-23",
        "value": 192.27843843077616
      },
      {
        "time": "2026-04-24",
        "value": 191.95325111576616
      },
      {
        "time": "2026-04-27",
        "value": 191.69129629973364
      },
      {
        "time": "2026-04-28",
        "value": 191.81511774574295
      },
      {
        "time": "2026-04-29",
        "value": 189.89519794995488
      },
      {
        "time": "2026-04-30",
        "value": 189.17637212868846
      },
      {
        "time": "2026-05-01",
        "value": 188.28600156623153
      },
      {
        "time": "2026-05-04",
        "value": 187.93503353216877
      },
      {
        "time": "2026-05-05",
        "value": 187.72475337928336
      }
    ],
    "supportLine": 198.04
  }
}