{
  "meta": {
    "ticker": "D",
    "name": "Dominion Energy, Inc.",
    "market": "NYQ",
    "price": 67.79,
    "change": -0.5,
    "changePercent": -0.73
  },
  "score": {
    "total": 31,
    "stars": 1.5,
    "note": "/ 100 (Win Rate: 22%)"
  },
  "raw_metrics": {
    "targetMA_label": "Daily 50MA",
    "targetMA_price": 65.29,
    "maDistance_pct": 3.83,
    "bb2Confluence_pct": 0.07,
    "bb3Confluence_pct": 1.77,
    "maKnock_count": 0,
    "expectedRsi": 42.29
  },
  "metrics": {
    "maDistance": "+3.83%",
    "bbConfluence": "0.07%",
    "maKnock": "0 times recently",
    "expectedRsi": "42.29"
  },
  "resistances": {
    "horizontal": [
      {
        "price": 67.9,
        "touches": 2,
        "strength_score": 1.529
      },
      {
        "price": 70.17,
        "touches": 1,
        "strength_score": 0.955
      }
    ],
    "trendline_clusters": []
  },
  "summary": "The SwingRatings algorithm indicates that D is currently testing its Daily 50MA support zone near $65.29. Based on historical price action, bounces from this level have yielded a win rate of 21.7%. This is a fresh test of the support, suggesting that optimal buy-side liquidity remains intact. In the event of a successful bounce, traders should monitor overhead supply, particularly a primary horizontal resistance at $67.90. This setup presents a structured risk-reward profile for swing positioning.",
  "chartData": {
    "candles": [
      {
        "time": "2025-11-24",
        "open": 59.47879969984125,
        "high": 60.098773552592306,
        "low": 58.71351785864231,
        "close": 59.67253875732422
      },
      {
        "time": "2025-11-25",
        "open": 59.83722090033364,
        "high": 60.147207824169406,
        "low": 58.93632024814356,
        "close": 59.614418029785156
      },
      {
        "time": "2025-11-26",
        "open": 59.91472132866785,
        "high": 60.67031775886584,
        "low": 59.72098225484187,
        "close": 60.583133697509766
      },
      {
        "time": "2025-11-28",
        "open": 60.6509414340326,
        "high": 60.9028044402382,
        "low": 60.495947962059354,
        "close": 60.80593490600586
      },
      {
        "time": "2025-12-01",
        "open": 60.73812611022374,
        "high": 60.74781158561105,
        "low": 58.781331197090665,
        "close": 58.89757537841797
      },
      {
        "time": "2025-12-02",
        "open": 59.07194307754749,
        "high": 59.07194307754749,
        "low": 58.15166771819598,
        "close": 58.46165466308594
      },
      {
        "time": "2025-12-03",
        "open": 58.6166489725587,
        "high": 59.004134506872255,
        "low": 57.967614952219805,
        "close": 58.151668548583984
      },
      {
        "time": "2025-12-04",
        "open": 58.171041456750096,
        "high": 58.481028396804525,
        "low": 57.77387045884687,
        "close": 57.967613220214844
      },
      {
        "time": "2025-12-05",
        "open": 57.78932254016306,
        "high": 57.93626720646448,
        "low": 57.27010758881596,
        "close": 57.29949951171875
      },
      {
        "time": "2025-12-08",
        "open": 57.40725438070376,
        "high": 57.79911427740566,
        "low": 56.79008008841975,
        "close": 57.250511169433594
      },
      {
        "time": "2025-12-09",
        "open": 57.554205521092484,
        "high": 57.955860252693725,
        "low": 57.03499430969537,
        "close": 57.27010726928711
      },
      {
        "time": "2025-12-10",
        "open": 57.21132608632625,
        "high": 57.25050908492743,
        "low": 56.43740487389781,
        "close": 56.87824630737305
      },
      {
        "time": "2025-12-11",
        "open": 56.82926067112956,
        "high": 57.534606960368826,
        "low": 56.721502754320476,
        "close": 56.98600387573242
      },
      {
        "time": "2025-12-12",
        "open": 57.06438265880983,
        "high": 58.21056674847168,
        "low": 57.054587842570925,
        "close": 58.12240219116211
      },
      {
        "time": "2025-12-15",
        "open": 58.220362195417,
        "high": 58.71998001211306,
        "low": 57.7501325629228,
        "close": 58.62201690673828
      },
      {
        "time": "2025-12-16",
        "open": 58.59262934067837,
        "high": 58.72977918447114,
        "low": 57.82850290989258,
        "close": 58.13219451904297
      },
      {
        "time": "2025-12-17",
        "open": 58.21056603954011,
        "high": 59.18041726571813,
        "low": 57.75013494085631,
        "close": 58.88652420043945
      },
      {
        "time": "2025-12-18",
        "open": 59.15102766966186,
        "high": 59.239195960848114,
        "low": 58.749372951380685,
        "close": 58.87672424316406
      },
      {
        "time": "2025-12-19",
        "open": 59.062859797127636,
        "high": 59.24899119670553,
        "low": 58.112601956168206,
        "close": 58.22036361694336
      },
      {
        "time": "2025-12-22",
        "open": 57.28969590645784,
        "high": 57.29949445891242,
        "low": 54.713225957665166,
        "close": 56.05534362792969
      },
      {
        "time": "2025-12-23",
        "open": 55.8300285768274,
        "high": 57.12316103011675,
        "low": 55.722266916211126,
        "close": 56.95661926269531
      },
      {
        "time": "2025-12-24",
        "open": 56.94682079956431,
        "high": 57.80890655517578,
        "low": 56.94682079956431,
        "close": 57.80890655517578
      },
      {
        "time": "2025-12-26",
        "open": 57.64237154569674,
        "high": 58.06361963018736,
        "low": 57.603184808289946,
        "close": 57.99504470825195
      },
      {
        "time": "2025-12-29",
        "open": 58.08321597525469,
        "high": 58.5142588976585,
        "low": 57.92647275464847,
        "close": 58.044029235839844
      },
      {
        "time": "2025-12-30",
        "open": 57.946063188150156,
        "high": 58.16158276990481,
        "low": 57.72074131645874,
        "close": 57.85789489746094
      },
      {
        "time": "2025-12-31",
        "open": 57.799115659550345,
        "high": 57.88728395156399,
        "low": 57.37786756849108,
        "close": 57.3974609375
      },
      {
        "time": "2026-01-02",
        "open": 57.710948106056996,
        "high": 58.17138294102624,
        "low": 57.083975237960274,
        "close": 58.03423309326172
      },
      {
        "time": "2026-01-05",
        "open": 57.76972578432753,
        "high": 58.03423065262951,
        "low": 56.329644969256556,
        "close": 57.49542236328125
      },
      {
        "time": "2026-01-06",
        "open": 57.603184342840265,
        "high": 58.00483905538201,
        "low": 57.39745957869636,
        "close": 57.52481460571289
      },
      {
        "time": "2026-01-07",
        "open": 57.70115312168129,
        "high": 57.779522861438295,
        "low": 55.75165586214107,
        "close": 55.91819763183594
      },
      {
        "time": "2026-01-08",
        "open": 55.87900964317528,
        "high": 57.12316053180009,
        "low": 55.869211090266724,
        "close": 56.623538970947266
      },
      {
        "time": "2026-01-09",
        "open": 56.7215036170837,
        "high": 57.32888307702674,
        "low": 56.7215036170837,
        "close": 56.79987335205078
      },
      {
        "time": "2026-01-12",
        "open": 56.790080922312,
        "high": 57.61298372782693,
        "low": 56.30025791276866,
        "close": 57.20153045654297
      },
      {
        "time": "2026-01-13",
        "open": 57.21132704781813,
        "high": 58.09300619253328,
        "low": 56.68231731875732,
        "close": 57.81870651245117
      },
      {
        "time": "2026-01-14",
        "open": 57.91667293775701,
        "high": 59.268585521650515,
        "low": 57.906878121643565,
        "close": 59.02367401123047
      },
      {
        "time": "2026-01-15",
        "open": 59.200011403564396,
        "high": 59.48410965641171,
        "low": 58.680800190263064,
        "close": 59.11184310913086
      },
      {
        "time": "2026-01-16",
        "open": 58.87672333583728,
        "high": 60.248229236031534,
        "low": 58.63181183487781,
        "close": 59.88576126098633
      },
      {
        "time": "2026-01-20",
        "open": 59.84657669067383,
        "high": 59.90535679837128,
        "low": 59.04326723740731,
        "close": 59.84657669067383
      },
      {
        "time": "2026-01-21",
        "open": 60.24823113133705,
        "high": 60.55192274741947,
        "low": 59.258790280637946,
        "close": 59.68003463745117
      },
      {
        "time": "2026-01-22",
        "open": 59.787795126808,
        "high": 59.9151501551908,
        "low": 58.68079782003225,
        "close": 58.71018600463867
      },
      {
        "time": "2026-01-23",
        "open": 58.5436450706854,
        "high": 58.66120528488765,
        "low": 57.78932091667926,
        "close": 58.38690185546875
      },
      {
        "time": "2026-01-26",
        "open": 58.63181278186023,
        "high": 59.47430895669675,
        "low": 58.63181278186023,
        "close": 59.013877868652344
      },
      {
        "time": "2026-01-27",
        "open": 58.97469017845284,
        "high": 59.944537629502726,
        "low": 58.73957349322845,
        "close": 59.88576126098633
      },
      {
        "time": "2026-01-28",
        "open": 59.79759298906474,
        "high": 60.30700935965935,
        "low": 59.21960169714518,
        "close": 59.474308013916016
      },
      {
        "time": "2026-01-29",
        "open": 59.83678085992149,
        "high": 60.1208753663424,
        "low": 59.092247789924535,
        "close": 59.59186935424805
      },
      {
        "time": "2026-01-30",
        "open": 59.62125922236523,
        "high": 59.70942751637906,
        "low": 58.4064964756251,
        "close": 58.9453010559082
      },
      {
        "time": "2026-02-02",
        "open": 59.043267941658335,
        "high": 59.72902092476247,
        "low": 58.31832821962181,
        "close": 58.80815124511719
      },
      {
        "time": "2026-02-03",
        "open": 58.945297133665576,
        "high": 60.4735462158639,
        "low": 58.945297133665576,
        "close": 60.17965316772461
      },
      {
        "time": "2026-02-04",
        "open": 60.67927144106558,
        "high": 61.62952924981906,
        "low": 60.49314004779602,
        "close": 61.061336517333984
      },
      {
        "time": "2026-02-05",
        "open": 61.28665377705902,
        "high": 61.541360087235425,
        "low": 60.81642415569677,
        "close": 61.247467041015625
      },
      {
        "time": "2026-02-06",
        "open": 61.70790272301859,
        "high": 62.13894561445737,
        "low": 60.404971758972984,
        "close": 61.061336517333984
      },
      {
        "time": "2026-02-09",
        "open": 61.00255665589345,
        "high": 61.14950131314969,
        "low": 60.365785263291,
        "close": 61.09072494506836
      },
      {
        "time": "2026-02-10",
        "open": 61.28665872214067,
        "high": 63.11859580387671,
        "low": 61.041747207687344,
        "close": 62.49162292480469
      },
      {
        "time": "2026-02-11",
        "open": 62.579786221983625,
        "high": 63.52024172843549,
        "low": 62.197724887875644,
        "close": 63.33411407470703
      },
      {
        "time": "2026-02-12",
        "open": 63.383098628569265,
        "high": 64.80358993446139,
        "low": 63.383098628569265,
        "close": 63.7945556640625
      },
      {
        "time": "2026-02-13",
        "open": 63.6769900749048,
        "high": 65.43055731386026,
        "low": 63.6769900749048,
        "close": 65.15625762939453
      },
      {
        "time": "2026-02-17",
        "open": 65.8518105221263,
        "high": 66.19468515441294,
        "low": 64.16681807305322,
        "close": 64.31376647949219
      },
      {
        "time": "2026-02-18",
        "open": 64.40192265303556,
        "high": 64.65663269275655,
        "low": 63.25573868544927,
        "close": 63.402687072753906
      },
      {
        "time": "2026-02-19",
        "open": 63.64760764986337,
        "high": 64.21580417573026,
        "low": 63.25574771912391,
        "close": 64.12763214111328
      },
      {
        "time": "2026-02-20",
        "open": 64.65663363487332,
        "high": 64.82317165499599,
        "low": 63.90230953107291,
        "close": 64.61744689941406
      },
      {
        "time": "2026-02-23",
        "open": 64.83297131546252,
        "high": 65.08768136324821,
        "low": 62.65815604198961,
        "close": 62.922664642333984
      },
      {
        "time": "2026-02-24",
        "open": 62.8638827439375,
        "high": 63.03042077205348,
        "low": 61.76668025778545,
        "close": 62.4426383972168
      },
      {
        "time": "2026-02-25",
        "open": 62.50141830557711,
        "high": 62.83449811772407,
        "low": 61.3846223875118,
        "close": 62.276100158691406
      },
      {
        "time": "2026-02-26",
        "open": 62.491620216350704,
        "high": 62.76591990479299,
        "low": 61.91362891780948,
        "close": 62.06057357788086
      },
      {
        "time": "2026-02-27",
        "open": 62.04869260664439,
        "high": 62.59324297026875,
        "low": 61.90018196128391,
        "close": 62.514034271240234
      },
      {
        "time": "2026-03-02",
        "open": 62.37542320905406,
        "high": 62.781358351879106,
        "low": 62.20711038789965,
        "close": 62.4249267578125
      },
      {
        "time": "2026-03-03",
        "open": 61.56355451059271,
        "high": 62.61304714497072,
        "low": 60.16753324909301,
        "close": 62.058597564697266
      },
      {
        "time": "2026-03-04",
        "open": 62.04869123778919,
        "high": 62.316014925795,
        "low": 61.17741822896866,
        "close": 61.949684143066406
      },
      {
        "time": "2026-03-05",
        "open": 61.71206756653578,
        "high": 62.484333505180466,
        "low": 61.434840894118736,
        "close": 62.375423431396484
      },
      {
        "time": "2026-03-06",
        "open": 62.04869220404977,
        "high": 62.77145835892005,
        "low": 61.424940699201336,
        "close": 62.61304473876953
      },
      {
        "time": "2026-03-09",
        "open": 62.46453171674006,
        "high": 62.61304614134239,
        "low": 61.434841274256655,
        "close": 62.28631591796875
      },
      {
        "time": "2026-03-10",
        "open": 61.811075815095734,
        "high": 62.71205401924692,
        "low": 61.65266218942779,
        "close": 62.10810089111328
      },
      {
        "time": "2026-03-11",
        "open": 61.90018213362751,
        "high": 62.19720720205409,
        "low": 61.37543772017793,
        "close": 61.59325408935547
      },
      {
        "time": "2026-03-12",
        "open": 61.43484157482151,
        "high": 63.127887894553325,
        "low": 61.33583447585471,
        "close": 62.217010498046875
      },
      {
        "time": "2026-03-13",
        "open": 63.07838272705526,
        "high": 63.21699417280477,
        "low": 62.464530420073764,
        "close": 62.58333969116211
      },
      {
        "time": "2026-03-16",
        "open": 63.18729188466138,
        "high": 63.2169932577839,
        "low": 62.56353661093839,
        "close": 62.791255950927734
      },
      {
        "time": "2026-03-17",
        "open": 63.30610284964822,
        "high": 63.395210748281066,
        "low": 62.38532248940171,
        "close": 62.40512466430664
      },
      {
        "time": "2026-03-18",
        "open": 62.21700943704172,
        "high": 62.2962143594887,
        "low": 61.57345197409614,
        "close": 61.58335494995117
      },
      {
        "time": "2026-03-19",
        "open": 61.54375187184904,
        "high": 61.73186687131612,
        "low": 59.56357967033925,
        "close": 60.41505432128906
      },
      {
        "time": "2026-03-20",
        "open": 60.49425868050631,
        "high": 60.65267230407275,
        "low": 58.504187298397945,
        "close": 58.79131317138672
      },
      {
        "time": "2026-03-23",
        "open": 59.54377502135251,
        "high": 59.98931450355802,
        "low": 58.78140830221832,
        "close": 59.22694778442383
      },
      {
        "time": "2026-03-24",
        "open": 58.8606188736749,
        "high": 60.296244461204275,
        "low": 58.731906624300606,
        "close": 59.672489166259766
      },
      {
        "time": "2026-03-25",
        "open": 60.13782915085209,
        "high": 60.682375730329255,
        "low": 59.731894015946,
        "close": 60.05862045288086
      },
      {
        "time": "2026-03-26",
        "open": 59.98931752135196,
        "high": 60.80118782893308,
        "low": 59.66258729233872,
        "close": 60.29624557495117
      },
      {
        "time": "2026-03-27",
        "open": 60.33584241243266,
        "high": 60.83088543649001,
        "low": 60.02891815471938,
        "close": 60.27643966674805
      },
      {
        "time": "2026-03-30",
        "open": 61.16751837025227,
        "high": 61.9001837499221,
        "low": 60.64277394310093,
        "close": 61.226924896240234
      },
      {
        "time": "2026-03-31",
        "open": 61.543752230025326,
        "high": 61.642759329925525,
        "low": 60.54376692426975,
        "close": 61.207122802734375
      },
      {
        "time": "2026-04-01",
        "open": 60.99920463589157,
        "high": 61.83087710293063,
        "low": 60.99920463589157,
        "close": 61.43484115600586
      },
      {
        "time": "2026-04-02",
        "open": 61.48434542578286,
        "high": 62.33582007783579,
        "low": 61.385338326330604,
        "close": 62.147705078125
      },
      {
        "time": "2026-04-06",
        "open": 61.81107421359439,
        "high": 62.31601645205348,
        "low": 61.48434399462541,
        "close": 61.60315704345703
      },
      {
        "time": "2026-04-07",
        "open": 61.55365147510383,
        "high": 62.523939183866446,
        "low": 61.55365147510383,
        "close": 62.06849670410156
      },
      {
        "time": "2026-04-08",
        "open": 61.30612781038906,
        "high": 62.60314192533848,
        "low": 61.177419340287095,
        "close": 62.57344055175781
      },
      {
        "time": "2026-04-09",
        "open": 61.94968518376871,
        "high": 63.939760302284014,
        "low": 61.94968518376871,
        "close": 63.47441864013672
      },
      {
        "time": "2026-04-10",
        "open": 63.46451517847398,
        "high": 64.48430261558113,
        "low": 63.29620236053065,
        "close": 63.593231201171875
      },
      {
        "time": "2026-04-13",
        "open": 63.444718360969745,
        "high": 63.51402408501116,
        "low": 61.959589228290255,
        "close": 62.34572219848633
      },
      {
        "time": "2026-04-14",
        "open": 62.16750700212286,
        "high": 63.23679802402465,
        "low": 61.563553878020386,
        "close": 63.07838439941406
      },
      {
        "time": "2026-04-15",
        "open": 62.613044599551934,
        "high": 62.77145821935022,
        "low": 61.56355200783912,
        "close": 61.76156997680664
      },
      {
        "time": "2026-04-16",
        "open": 61.60315591564027,
        "high": 62.09819894607292,
        "low": 61.06850853632214,
        "close": 61.86057662963867
      },
      {
        "time": "2026-04-17",
        "open": 61.50414528507024,
        "high": 62.048691865309905,
        "low": 60.9496995060096,
        "close": 61.801170349121094
      },
      {
        "time": "2026-04-20",
        "open": 61.74176849021527,
        "high": 62.42492652504314,
        "low": 61.35563552370914,
        "close": 61.60315704345703
      },
      {
        "time": "2026-04-21",
        "open": 61.652661636361074,
        "high": 61.72196736091416,
        "low": 60.40515104064814,
        "close": 60.48435974121094
      },
      {
        "time": "2026-04-22",
        "open": 60.95960122941151,
        "high": 61.167518405169936,
        "low": 59.840802872378156,
        "close": 60.34574890136719
      },
      {
        "time": "2026-04-23",
        "open": 60.93979613152138,
        "high": 61.979385737335626,
        "low": 60.702177592587105,
        "close": 61.90018081665039
      },
      {
        "time": "2026-04-24",
        "open": 61.83087485257015,
        "high": 62.27641433242524,
        "low": 61.26652610371321,
        "close": 61.95958709716797
      },
      {
        "time": "2026-04-27",
        "open": 61.801170025477184,
        "high": 62.47442884813528,
        "low": 61.75166647787439,
        "close": 61.88037872314453
      },
      {
        "time": "2026-04-28",
        "open": 62.424927448369495,
        "high": 62.830862595685076,
        "low": 61.9199852024418,
        "close": 62.26651382446289
      },
      {
        "time": "2026-04-29",
        "open": 61.92988227074733,
        "high": 62.662547616655935,
        "low": 61.79127082670806,
        "close": 61.88037872314453
      },
      {
        "time": "2026-04-30",
        "open": 62.57344256095654,
        "high": 64.02886656632145,
        "low": 62.147705233863206,
        "close": 63.86055374145508
      },
      {
        "time": "2026-05-01",
        "open": 63.860552318538325,
        "high": 64.95954847436724,
        "low": 63.11798775669485,
        "close": 63.30610275268555
      },
      {
        "time": "2026-05-04",
        "open": 62.77145960074258,
        "high": 63.49421821615411,
        "low": 62.04869343157365,
        "close": 62.32592010498047
      },
      {
        "time": "2026-05-05",
        "open": 62.58334066288973,
        "high": 63.12788725545162,
        "low": 62.068495444341444,
        "close": 62.36552429199219
      },
      {
        "time": "2026-05-06",
        "open": 62.29621290578973,
        "high": 62.345720230152324,
        "low": 60.99920258806694,
        "close": 61.02890396118164
      },
      {
        "time": "2026-05-07",
        "open": 60.910094831844006,
        "high": 61.08831062469896,
        "low": 60.56356244490222,
        "close": 60.999202728271484
      },
      {
        "time": "2026-05-08",
        "open": 61.24672684820997,
        "high": 61.48434539753773,
        "low": 60.43485654706241,
        "close": 61.27642822265625
      },
      {
        "time": "2026-05-11",
        "open": 61.73186406153943,
        "high": 62.00909072541015,
        "low": 61.137813938876675,
        "close": 61.93978500366211
      },
      {
        "time": "2026-05-12",
        "open": 62.09820086059796,
        "high": 62.47443085597359,
        "low": 61.51404991560256,
        "close": 62.29621505737305
      },
      {
        "time": "2026-05-13",
        "open": 61.47444644765618,
        "high": 62.55364045383317,
        "low": 61.21702572202735,
        "close": 62.098201751708984
      },
      {
        "time": "2026-05-14",
        "open": 61.90018270330674,
        "high": 62.38532277159664,
        "low": 61.90018270330674,
        "close": 62.34572219848633
      },
      {
        "time": "2026-05-15",
        "open": 62.23680976975813,
        "high": 62.49423048118991,
        "low": 61.098209300364076,
        "close": 61.118011474609375
      },
      {
        "time": "2026-05-18",
        "open": 67.95950778984054,
        "high": 68.28623800848337,
        "low": 65.79121686181115,
        "close": 66.89021301269531
      },
      {
        "time": "2026-05-19",
        "open": 66.53377900490611,
        "high": 67.78128953295325,
        "low": 65.64270761005805,
        "close": 67.45455932617188
      },
      {
        "time": "2026-05-20",
        "open": 67.5238668216862,
        "high": 68.20702862586505,
        "low": 66.64269082539384,
        "close": 67.05853271484375
      },
      {
        "time": "2026-05-21",
        "open": 66.92981429450722,
        "high": 67.8109902592404,
        "low": 66.91001589750785,
        "close": 67.61297607421875
      },
      {
        "time": "2026-05-22",
        "open": 67.5337700044833,
        "high": 67.90010457014944,
        "low": 66.7615040776127,
        "close": 66.9991226196289
      },
      {
        "time": "2026-05-26",
        "open": 67.02882568044306,
        "high": 67.4545630038908,
        "low": 66.53378263242278,
        "close": 66.61299133300781
      },
      {
        "time": "2026-05-27",
        "open": 66.50408158455856,
        "high": 66.99912463500863,
        "low": 66.20706028654303,
        "close": 66.53378295898438
      },
      {
        "time": "2026-05-28",
        "open": 67.16743668052266,
        "high": 67.70208407526093,
        "low": 66.70210256365095,
        "close": 66.71199798583984
      },
      {
        "time": "2026-05-29",
        "open": 66.75,
        "high": 67.11000061035156,
        "low": 65.83000183105469,
        "close": 66.94000244140625
      },
      {
        "time": "2026-06-01",
        "open": 66.25,
        "high": 66.43000030517578,
        "low": 64.55000305175781,
        "close": 64.61000061035156
      },
      {
        "time": "2026-06-02",
        "open": 64.5999984741211,
        "high": 66.48999786376953,
        "low": 64.5999984741211,
        "close": 66.47000122070312
      },
      {
        "time": "2026-06-03",
        "open": 66.4000015258789,
        "high": 67.0999984741211,
        "low": 65.45999908447266,
        "close": 65.45999908447266
      },
      {
        "time": "2026-06-04",
        "open": 65.61000061035156,
        "high": 66.95999908447266,
        "low": 65.47000122070312,
        "close": 66.5
      },
      {
        "time": "2026-06-05",
        "open": 66.19999694824219,
        "high": 67.5199966430664,
        "low": 66.19999694824219,
        "close": 66.9000015258789
      },
      {
        "time": "2026-06-08",
        "open": 66.9800033569336,
        "high": 67.19999694824219,
        "low": 65.51000213623047,
        "close": 65.5199966430664
      },
      {
        "time": "2026-06-09",
        "open": 65.7699966430664,
        "high": 66.4000015258789,
        "low": 65.47000122070312,
        "close": 66.25
      },
      {
        "time": "2026-06-10",
        "open": 66.83000183105469,
        "high": 66.95999908447266,
        "low": 66.16000366210938,
        "close": 66.7699966430664
      },
      {
        "time": "2026-06-11",
        "open": 67.0,
        "high": 67.45999908447266,
        "low": 66.61000061035156,
        "close": 66.69000244140625
      },
      {
        "time": "2026-06-12",
        "open": 67.22000122070312,
        "high": 68.12999725341797,
        "low": 67.12000274658203,
        "close": 67.91000366210938
      },
      {
        "time": "2026-06-15",
        "open": 67.54000091552734,
        "high": 68.62999725341797,
        "low": 67.33000183105469,
        "close": 68.1500015258789
      },
      {
        "time": "2026-06-16",
        "open": 68.13999938964844,
        "high": 69.25,
        "low": 68.11000061035156,
        "close": 68.5
      },
      {
        "time": "2026-06-17",
        "open": 67.97000122070312,
        "high": 68.75,
        "low": 67.87000274658203,
        "close": 68.0199966430664
      },
      {
        "time": "2026-06-18",
        "open": 68.11000061035156,
        "high": 69.27999877929688,
        "low": 68.08000183105469,
        "close": 68.41000366210938
      },
      {
        "time": "2026-06-22",
        "open": 68.80000305175781,
        "high": 69.19000244140625,
        "low": 67.87000274658203,
        "close": 68.04000091552734
      },
      {
        "time": "2026-06-23",
        "open": 68.20999908447266,
        "high": 68.87000274658203,
        "low": 68.06999969482422,
        "close": 68.44999694824219
      },
      {
        "time": "2026-06-24",
        "open": 68.5999984741211,
        "high": 69.43000030517578,
        "low": 68.41000366210938,
        "close": 69.26000213623047
      },
      {
        "time": "2026-06-25",
        "open": 69.62999725341797,
        "high": 70.16999816894531,
        "low": 68.77999877929688,
        "close": 69.51000213623047
      },
      {
        "time": "2026-06-26",
        "open": 69.58999633789062,
        "high": 69.8499984741211,
        "low": 68.88999938964844,
        "close": 69.38999938964844
      },
      {
        "time": "2026-06-29",
        "open": 69.38999938964844,
        "high": 69.9000015258789,
        "low": 68.7699966430664,
        "close": 69.18000030517578
      },
      {
        "time": "2026-06-30",
        "open": 68.91999816894531,
        "high": 69.30999755859375,
        "low": 68.23999786376953,
        "close": 68.29000091552734
      },
      {
        "time": "2026-07-01",
        "open": 68.36000061035156,
        "high": 68.52999877929688,
        "low": 67.375,
        "close": 67.79000091552734
      }
    ],
    "ma_target": [
      {
        "time": "2025-11-24",
        "value": 58.70673919677734
      },
      {
        "time": "2025-11-25",
        "value": 58.748199920654294
      },
      {
        "time": "2025-11-26",
        "value": 58.80516014099121
      },
      {
        "time": "2025-11-28",
        "value": 58.863863983154296
      },
      {
        "time": "2025-12-01",
        "value": 58.88226951599121
      },
      {
        "time": "2025-12-02",
        "value": 58.89253784179687
      },
      {
        "time": "2025-12-03",
        "value": 58.871419982910155
      },
      {
        "time": "2025-12-04",
        "value": 58.84855834960938
      },
      {
        "time": "2025-12-05",
        "value": 58.83848976135254
      },
      {
        "time": "2025-12-08",
        "value": 58.81465431213379
      },
      {
        "time": "2025-12-09",
        "value": 58.779780044555665
      },
      {
        "time": "2025-12-10",
        "value": 58.732225036621095
      },
      {
        "time": "2025-12-11",
        "value": 58.69205612182617
      },
      {
        "time": "2025-12-12",
        "value": 58.670934143066404
      },
      {
        "time": "2025-12-15",
        "value": 58.651279830932616
      },
      {
        "time": "2025-12-16",
        "value": 58.62241027832031
      },
      {
        "time": "2025-12-17",
        "value": 58.62083312988281
      },
      {
        "time": "2025-12-18",
        "value": 58.6248722076416
      },
      {
        "time": "2025-12-19",
        "value": 58.621790084838864
      },
      {
        "time": "2025-12-22",
        "value": 58.56165184020996
      },
      {
        "time": "2025-12-23",
        "value": 58.51237060546875
      },
      {
        "time": "2025-12-24",
        "value": 58.47664779663086
      },
      {
        "time": "2025-12-26",
        "value": 58.441354217529295
      },
      {
        "time": "2025-12-29",
        "value": 58.42777069091797
      },
      {
        "time": "2025-12-30",
        "value": 58.4112393951416
      },
      {
        "time": "2025-12-31",
        "value": 58.36864387512207
      },
      {
        "time": "2026-01-02",
        "value": 58.35002090454102
      },
      {
        "time": "2026-01-05",
        "value": 58.32004035949707
      },
      {
        "time": "2026-01-06",
        "value": 58.29491004943848
      },
      {
        "time": "2026-01-07",
        "value": 58.23028518676758
      },
      {
        "time": "2026-01-08",
        "value": 58.18480445861817
      },
      {
        "time": "2026-01-09",
        "value": 58.16571197509766
      },
      {
        "time": "2026-01-12",
        "value": 58.16685836791992
      },
      {
        "time": "2026-01-13",
        "value": 58.170079956054686
      },
      {
        "time": "2026-01-14",
        "value": 58.21348152160645
      },
      {
        "time": "2026-01-15",
        "value": 58.262521209716795
      },
      {
        "time": "2026-01-16",
        "value": 58.3109587097168
      },
      {
        "time": "2026-01-20",
        "value": 58.35144416809082
      },
      {
        "time": "2026-01-21",
        "value": 58.372905578613285
      },
      {
        "time": "2026-01-22",
        "value": 58.35404586791992
      },
      {
        "time": "2026-01-23",
        "value": 58.342476272583006
      },
      {
        "time": "2026-01-26",
        "value": 58.33705261230469
      },
      {
        "time": "2026-01-27",
        "value": 58.34577301025391
      },
      {
        "time": "2026-01-28",
        "value": 58.35595153808594
      },
      {
        "time": "2026-01-29",
        "value": 58.374487228393555
      },
      {
        "time": "2026-01-30",
        "value": 58.36187980651855
      },
      {
        "time": "2026-02-02",
        "value": 58.347498092651364
      },
      {
        "time": "2026-02-03",
        "value": 58.38495796203613
      },
      {
        "time": "2026-02-04",
        "value": 58.42765190124512
      },
      {
        "time": "2026-02-05",
        "value": 58.461669006347655
      },
      {
        "time": "2026-02-06",
        "value": 58.48944496154785
      },
      {
        "time": "2026-02-09",
        "value": 58.518971099853516
      },
      {
        "time": "2026-02-10",
        "value": 58.557140884399416
      },
      {
        "time": "2026-02-11",
        "value": 58.60770446777344
      },
      {
        "time": "2026-02-12",
        "value": 58.705644073486326
      },
      {
        "time": "2026-02-13",
        "value": 58.8395361328125
      },
      {
        "time": "2026-02-17",
        "value": 58.962778091430664
      },
      {
        "time": "2026-02-18",
        "value": 59.07147956848144
      },
      {
        "time": "2026-02-19",
        "value": 59.208042221069334
      },
      {
        "time": "2026-02-20",
        "value": 59.35538093566895
      },
      {
        "time": "2026-02-23",
        "value": 59.46843208312988
      },
      {
        "time": "2026-02-24",
        "value": 59.579719924926756
      },
      {
        "time": "2026-02-25",
        "value": 59.685521850585936
      },
      {
        "time": "2026-02-26",
        "value": 59.764285278320315
      },
      {
        "time": "2026-02-27",
        "value": 59.84212562561035
      },
      {
        "time": "2026-03-02",
        "value": 59.927980270385746
      },
      {
        "time": "2026-03-03",
        "value": 59.9914217376709
      },
      {
        "time": "2026-03-04",
        "value": 60.052880935668945
      },
      {
        "time": "2026-03-05",
        "value": 60.13598213195801
      },
      {
        "time": "2026-03-06",
        "value": 60.26713615417481
      },
      {
        "time": "2026-03-09",
        "value": 60.37373008728027
      },
      {
        "time": "2026-03-10",
        "value": 60.45971397399902
      },
      {
        "time": "2026-03-11",
        "value": 60.531678161621095
      },
      {
        "time": "2026-03-12",
        "value": 60.61513778686523
      },
      {
        "time": "2026-03-13",
        "value": 60.709646682739255
      },
      {
        "time": "2026-03-16",
        "value": 60.817522583007815
      },
      {
        "time": "2026-03-17",
        "value": 60.90494041442871
      },
      {
        "time": "2026-03-18",
        "value": 60.98669906616211
      },
      {
        "time": "2026-03-19",
        "value": 61.04450386047363
      },
      {
        "time": "2026-03-20",
        "value": 61.10196617126465
      },
      {
        "time": "2026-03-23",
        "value": 61.15403434753418
      },
      {
        "time": "2026-03-24",
        "value": 61.21148666381836
      },
      {
        "time": "2026-03-25",
        "value": 61.26862846374512
      },
      {
        "time": "2026-03-26",
        "value": 61.318179244995115
      },
      {
        "time": "2026-03-27",
        "value": 61.34323455810547
      },
      {
        "time": "2026-03-30",
        "value": 61.385536193847656
      },
      {
        "time": "2026-03-31",
        "value": 61.41196342468262
      },
      {
        "time": "2026-04-01",
        "value": 61.44372871398926
      },
      {
        "time": "2026-04-02",
        "value": 61.49308212280273
      },
      {
        "time": "2026-04-06",
        "value": 61.5509415435791
      },
      {
        "time": "2026-04-07",
        "value": 61.62457344055176
      },
      {
        "time": "2026-04-08",
        "value": 61.695764694213864
      },
      {
        "time": "2026-04-09",
        "value": 61.76753784179687
      },
      {
        "time": "2026-04-10",
        "value": 61.849916305541996
      },
      {
        "time": "2026-04-13",
        "value": 61.90499336242676
      },
      {
        "time": "2026-04-14",
        "value": 61.987655029296874
      },
      {
        "time": "2026-04-15",
        "value": 62.04672340393066
      },
      {
        "time": "2026-04-16",
        "value": 62.08034187316895
      },
      {
        "time": "2026-04-17",
        "value": 62.09513854980469
      },
      {
        "time": "2026-04-20",
        "value": 62.102252349853515
      },
      {
        "time": "2026-04-21",
        "value": 62.090712814331056
      },
      {
        "time": "2026-04-22",
        "value": 62.07581329345703
      },
      {
        "time": "2026-04-23",
        "value": 62.06398445129395
      },
      {
        "time": "2026-04-24",
        "value": 62.036493911743165
      },
      {
        "time": "2026-04-27",
        "value": 61.9982103729248
      },
      {
        "time": "2026-04-28",
        "value": 61.94041549682617
      },
      {
        "time": "2026-04-29",
        "value": 61.89174774169922
      },
      {
        "time": "2026-04-30",
        "value": 61.90090507507324
      },
      {
        "time": "2026-05-01",
        "value": 61.884474487304686
      },
      {
        "time": "2026-05-04",
        "value": 61.83864395141602
      },
      {
        "time": "2026-05-05",
        "value": 61.82750114440918
      },
      {
        "time": "2026-05-06",
        "value": 61.799226455688476
      },
      {
        "time": "2026-05-07",
        "value": 61.77368850708008
      },
      {
        "time": "2026-05-08",
        "value": 61.75800559997558
      },
      {
        "time": "2026-05-11",
        "value": 61.746520614624025
      },
      {
        "time": "2026-05-12",
        "value": 61.743946380615235
      },
      {
        "time": "2026-05-13",
        "value": 61.74473846435547
      },
      {
        "time": "2026-05-14",
        "value": 61.752659225463866
      },
      {
        "time": "2026-05-15",
        "value": 61.72751098632813
      },
      {
        "time": "2026-05-18",
        "value": 61.81305435180664
      },
      {
        "time": "2026-05-19",
        "value": 61.916419219970706
      },
      {
        "time": "2026-05-20",
        "value": 62.015427856445314
      },
      {
        "time": "2026-05-21",
        "value": 62.13582229614258
      },
      {
        "time": "2026-05-22",
        "value": 62.231464538574215
      },
      {
        "time": "2026-05-26",
        "value": 62.31205757141113
      },
      {
        "time": "2026-05-27",
        "value": 62.38690811157227
      },
      {
        "time": "2026-05-28",
        "value": 62.47304557800293
      },
      {
        "time": "2026-05-29",
        "value": 62.58017852783203
      },
      {
        "time": "2026-06-01",
        "value": 62.66407745361328
      },
      {
        "time": "2026-06-02",
        "value": 62.81765121459961
      },
      {
        "time": "2026-06-03",
        "value": 62.942312240600586
      },
      {
        "time": "2026-06-04",
        "value": 63.07886245727539
      },
      {
        "time": "2026-06-05",
        "value": 63.21569007873535
      },
      {
        "time": "2026-06-08",
        "value": 63.320165100097654
      },
      {
        "time": "2026-06-09",
        "value": 63.439636306762694
      },
      {
        "time": "2026-06-10",
        "value": 63.55049774169922
      },
      {
        "time": "2026-06-11",
        "value": 63.660155334472655
      },
      {
        "time": "2026-06-12",
        "value": 63.789658584594726
      },
      {
        "time": "2026-06-15",
        "value": 63.909704513549805
      },
      {
        "time": "2026-06-16",
        "value": 64.04764137268066
      },
      {
        "time": "2026-06-17",
        "value": 64.16667137145996
      },
      {
        "time": "2026-06-18",
        "value": 64.283402633667
      },
      {
        "time": "2026-06-22",
        "value": 64.37471427917481
      },
      {
        "time": "2026-06-23",
        "value": 64.47184959411621
      },
      {
        "time": "2026-06-24",
        "value": 64.6101351928711
      },
      {
        "time": "2026-06-25",
        "value": 64.73876754760742
      },
      {
        "time": "2026-06-26",
        "value": 64.89133613586426
      },
      {
        "time": "2026-06-29",
        "value": 65.037724609375
      },
      {
        "time": "2026-06-30",
        "value": 65.16750122070313
      },
      {
        "time": "2026-07-01",
        "value": 65.29123809814453
      }
    ],
    "bbLower": [
      {
        "time": "2025-11-24",
        "value": 56.57870368763986
      },
      {
        "time": "2025-11-25",
        "value": 56.65025005230686
      },
      {
        "time": "2025-11-26",
        "value": 56.76718436742343
      },
      {
        "time": "2025-11-28",
        "value": 56.81459142038733
      },
      {
        "time": "2025-12-01",
        "value": 57.14414260773856
      },
      {
        "time": "2025-12-02",
        "value": 57.550582843665524
      },
      {
        "time": "2025-12-03",
        "value": 57.70639293081105
      },
      {
        "time": "2025-12-04",
        "value": 57.739282233677116
      },
      {
        "time": "2025-12-05",
        "value": 57.47136132336508
      },
      {
        "time": "2025-12-08",
        "value": 57.18329177279896
      },
      {
        "time": "2025-12-09",
        "value": 56.94840980723106
      },
      {
        "time": "2025-12-10",
        "value": 56.647682721072066
      },
      {
        "time": "2025-12-11",
        "value": 56.40998914381467
      },
      {
        "time": "2025-12-12",
        "value": 56.360187892535635
      },
      {
        "time": "2025-12-15",
        "value": 56.35810737845809
      },
      {
        "time": "2025-12-16",
        "value": 56.32018452780491
      },
      {
        "time": "2025-12-17",
        "value": 56.32707369876779
      },
      {
        "time": "2025-12-18",
        "value": 56.35254446968105
      },
      {
        "time": "2025-12-19",
        "value": 56.32003545844164
      },
      {
        "time": "2025-12-22",
        "value": 55.954988603859505
      },
      {
        "time": "2025-12-23",
        "value": 55.82941681219029
      },
      {
        "time": "2025-12-24",
        "value": 55.82515336509753
      },
      {
        "time": "2025-12-26",
        "value": 55.99675784832006
      },
      {
        "time": "2025-12-29",
        "value": 56.336833506572994
      },
      {
        "time": "2025-12-30",
        "value": 56.36412821634292
      },
      {
        "time": "2025-12-31",
        "value": 56.3355734776662
      },
      {
        "time": "2026-01-02",
        "value": 56.33568802805925
      },
      {
        "time": "2026-01-05",
        "value": 56.31277039235643
      },
      {
        "time": "2026-01-06",
        "value": 56.33384500043903
      },
      {
        "time": "2026-01-07",
        "value": 56.06940467920399
      },
      {
        "time": "2026-01-08",
        "value": 55.98164843676075
      },
      {
        "time": "2026-01-09",
        "value": 55.97028492824711
      },
      {
        "time": "2026-01-12",
        "value": 55.99497310426854
      },
      {
        "time": "2026-01-13",
        "value": 55.99283418520169
      },
      {
        "time": "2026-01-14",
        "value": 55.95452089982875
      },
      {
        "time": "2026-01-15",
        "value": 55.89455047033067
      },
      {
        "time": "2026-01-16",
        "value": 55.7658180776551
      },
      {
        "time": "2026-01-20",
        "value": 55.661925261286704
      },
      {
        "time": "2026-01-21",
        "value": 55.58421768327836
      },
      {
        "time": "2026-01-22",
        "value": 55.84640857728887
      },
      {
        "time": "2026-01-23",
        "value": 55.965321151309915
      },
      {
        "time": "2026-01-26",
        "value": 55.98869755212338
      },
      {
        "time": "2026-01-27",
        "value": 55.949868808862135
      },
      {
        "time": "2026-01-28",
        "value": 55.95776426913768
      },
      {
        "time": "2026-01-29",
        "value": 55.98602518281182
      },
      {
        "time": "2026-01-30",
        "value": 56.09458059009306
      },
      {
        "time": "2026-02-02",
        "value": 56.13635416647942
      },
      {
        "time": "2026-02-03",
        "value": 56.2067810945733
      },
      {
        "time": "2026-02-04",
        "value": 56.21844911314716
      },
      {
        "time": "2026-02-05",
        "value": 56.633260639084966
      },
      {
        "time": "2026-02-06",
        "value": 56.98002630242935
      },
      {
        "time": "2026-02-09",
        "value": 57.368015200311305
      },
      {
        "time": "2026-02-10",
        "value": 57.529336996859584
      },
      {
        "time": "2026-02-11",
        "value": 57.49480064573805
      },
      {
        "time": "2026-02-12",
        "value": 57.302144417790444
      },
      {
        "time": "2026-02-13",
        "value": 56.9787945445054
      },
      {
        "time": "2026-02-17",
        "value": 56.86962615896946
      },
      {
        "time": "2026-02-18",
        "value": 56.9172437028136
      },
      {
        "time": "2026-02-19",
        "value": 56.96580905210011
      },
      {
        "time": "2026-02-20",
        "value": 57.174999157486646
      },
      {
        "time": "2026-02-23",
        "value": 57.607627089968815
      },
      {
        "time": "2026-02-24",
        "value": 57.96361069473198
      },
      {
        "time": "2026-02-25",
        "value": 58.19110228028469
      },
      {
        "time": "2026-02-26",
        "value": 58.50242234100764
      },
      {
        "time": "2026-02-27",
        "value": 58.84067239673743
      },
      {
        "time": "2026-03-02",
        "value": 59.37506413290957
      },
      {
        "time": "2026-03-03",
        "value": 60.019820476926974
      },
      {
        "time": "2026-03-04",
        "value": 60.33654687618628
      },
      {
        "time": "2026-03-05",
        "value": 60.51902147379795
      },
      {
        "time": "2026-03-06",
        "value": 60.6969533390975
      },
      {
        "time": "2026-03-09",
        "value": 60.90027849031346
      },
      {
        "time": "2026-03-10",
        "value": 61.091389683225024
      },
      {
        "time": "2026-03-11",
        "value": 60.962128304217046
      },
      {
        "time": "2026-03-12",
        "value": 60.89317287463616
      },
      {
        "time": "2026-03-13",
        "value": 60.87695749901563
      },
      {
        "time": "2026-03-16",
        "value": 61.0894930875934
      },
      {
        "time": "2026-03-17",
        "value": 61.1778004865501
      },
      {
        "time": "2026-03-18",
        "value": 61.073998516334086
      },
      {
        "time": "2026-03-19",
        "value": 60.82042574283907
      },
      {
        "time": "2026-03-20",
        "value": 60.20376928042577
      },
      {
        "time": "2026-03-23",
        "value": 59.69982793378532
      },
      {
        "time": "2026-03-24",
        "value": 59.38472358398888
      },
      {
        "time": "2026-03-25",
        "value": 59.18457510295232
      },
      {
        "time": "2026-03-26",
        "value": 59.04347794436788
      },
      {
        "time": "2026-03-27",
        "value": 58.92303913634186
      },
      {
        "time": "2026-03-30",
        "value": 58.90924279575193
      },
      {
        "time": "2026-03-31",
        "value": 58.88986884967611
      },
      {
        "time": "2026-04-01",
        "value": 58.88231565243495
      },
      {
        "time": "2026-04-02",
        "value": 58.89035433206911
      },
      {
        "time": "2026-04-06",
        "value": 58.91712399634533
      },
      {
        "time": "2026-04-07",
        "value": 58.925170414236916
      },
      {
        "time": "2026-04-08",
        "value": 58.9018195497083
      },
      {
        "time": "2026-04-09",
        "value": 58.796059864887376
      },
      {
        "time": "2026-04-10",
        "value": 58.69822660545672
      },
      {
        "time": "2026-04-13",
        "value": 58.70595495800344
      },
      {
        "time": "2026-04-14",
        "value": 58.68659253779584
      },
      {
        "time": "2026-04-15",
        "value": 58.68938943533879
      },
      {
        "time": "2026-04-16",
        "value": 58.69545946486603
      },
      {
        "time": "2026-04-17",
        "value": 58.79433581145839
      },
      {
        "time": "2026-04-20",
        "value": 59.228832067935876
      },
      {
        "time": "2026-04-21",
        "value": 59.48729375683036
      },
      {
        "time": "2026-04-22",
        "value": 59.62644900703667
      },
      {
        "time": "2026-04-23",
        "value": 59.85494550214795
      },
      {
        "time": "2026-04-24",
        "value": 60.058931080031755
      },
      {
        "time": "2026-04-27",
        "value": 60.28962104547398
      },
      {
        "time": "2026-04-28",
        "value": 60.3669306645566
      },
      {
        "time": "2026-04-29",
        "value": 60.43822101997423
      },
      {
        "time": "2026-04-30",
        "value": 60.38790016871801
      },
      {
        "time": "2026-05-01",
        "value": 60.370920964812804
      },
      {
        "time": "2026-05-04",
        "value": 60.42598173954535
      },
      {
        "time": "2026-05-05",
        "value": 60.44112842211672
      },
      {
        "time": "2026-05-06",
        "value": 60.29730471745127
      },
      {
        "time": "2026-05-07",
        "value": 60.211909900025496
      },
      {
        "time": "2026-05-08",
        "value": 60.217289531761736
      },
      {
        "time": "2026-05-11",
        "value": 60.20832463922182
      },
      {
        "time": "2026-05-12",
        "value": 60.246096273323495
      },
      {
        "time": "2026-05-13",
        "value": 60.260240537914605
      },
      {
        "time": "2026-05-14",
        "value": 60.2714977733236
      },
      {
        "time": "2026-05-15",
        "value": 60.20231123988012
      },
      {
        "time": "2026-05-18",
        "value": 59.386009231588474
      },
      {
        "time": "2026-05-19",
        "value": 58.988657438659416
      },
      {
        "time": "2026-05-20",
        "value": 58.93863813305815
      },
      {
        "time": "2026-05-21",
        "value": 58.72518378103633
      },
      {
        "time": "2026-05-22",
        "value": 58.696845655926566
      },
      {
        "time": "2026-05-26",
        "value": 58.77778706210933
      },
      {
        "time": "2026-05-27",
        "value": 58.8673312113704
      },
      {
        "time": "2026-05-28",
        "value": 59.03594332944765
      },
      {
        "time": "2026-05-29",
        "value": 59.03464726677482
      },
      {
        "time": "2026-06-01",
        "value": 59.113515819808484
      },
      {
        "time": "2026-06-02",
        "value": 59.31533604368072
      },
      {
        "time": "2026-06-03",
        "value": 59.546622700051635
      },
      {
        "time": "2026-06-04",
        "value": 60.03942692225468
      },
      {
        "time": "2026-06-05",
        "value": 60.60807100902784
      },
      {
        "time": "2026-06-08",
        "value": 61.18658968656513
      },
      {
        "time": "2026-06-09",
        "value": 61.7023434825065
      },
      {
        "time": "2026-06-10",
        "value": 62.20996454296333
      },
      {
        "time": "2026-06-11",
        "value": 62.859013486307646
      },
      {
        "time": "2026-06-12",
        "value": 63.537434563677635
      },
      {
        "time": "2026-06-15",
        "value": 65.09254746699925
      },
      {
        "time": "2026-06-16",
        "value": 64.99260410270301
      },
      {
        "time": "2026-06-17",
        "value": 64.96241884558488
      },
      {
        "time": "2026-06-18",
        "value": 64.90420804864027
      },
      {
        "time": "2026-06-22",
        "value": 64.88542327095342
      },
      {
        "time": "2026-06-23",
        "value": 64.84743521218711
      },
      {
        "time": "2026-06-24",
        "value": 64.76677260043414
      },
      {
        "time": "2026-06-25",
        "value": 64.71007056436105
      },
      {
        "time": "2026-06-26",
        "value": 64.69454656699445
      },
      {
        "time": "2026-06-29",
        "value": 64.70586739673294
      },
      {
        "time": "2026-06-30",
        "value": 65.20880895061806
      },
      {
        "time": "2026-07-01",
        "value": 65.3381882435614
      }
    ],
    "supportLine": 60.73
  }
}